Workbook

Sheet Budgets 2627
B3: French league (Betclic Elite)
B4: Nation | C4: Club | D4: Total Budget | E4: Gross salary budget | F4: Salary % from total budget | G4: Budget increase from the last season | H4: Place in the national league after the regular season | I4: Participation in European tournament
B5: France | C5: Paris | F5: =+E5/D5 -> #DIV/0! | H5: - | I5: -
B6: France | C6: Monaco | F6: =+E6/D6 -> #DIV/0! | H6: - | I6: -
B7: France | C7: Nanterre | F7: =+E7/D7 -> #DIV/0! | H7: - | I7: -
B8: France | C8: Asvel | F8: =+E8/D8 -> #DIV/0! | H8: - | I8: -
B9: France | C9: Cholet | F9: =+E9/D9 -> #DIV/0! | H9: - | I9: -
B10: France | C10: Le Mans | F10: =+E10/D10 -> #DIV/0! | H10: - | I10: -
B11: France | C11: Bourg-en-Bresse | F11: =+E11/D11 -> #DIV/0! | H11: - | I11: -
B12: France | C12: Strasbourg | F12: =+E12/D12 -> #DIV/0! | H12: - | I12: -
B13: France | C13: Chalon | F13: =+E13/D13 -> #DIV/0! | H13: - | I13: -
B14: France | C14: Nancy | F14: =+E14/D14 -> #DIV/0! | H14: - | I14: -
B15: France | C15: Dijon | F15: =+E15/D15 -> #DIV/0! | H15: - | I15: -
B16: France | C16: Boulazac | F16: =+E16/D16 -> #DIV/0! | H16: - | I16: -
... B20: France | C20: Le Portel | F20: =+E20/D20 -> #DIV/0! | H20: - | I20: -
E21: League average | F21: =average(F5:F20) -> #DIV/0!
B23: German league (easyCredit BBL)
B24: Nation | C24: Club | D24: Total Budget | E24: Gross salary budget | F24: Salary % from total budget | G24: Budget increase from the last season | H24: Place in the national league after the regular season | I24: Participation in European tournament
B25: Germany | C25: FC Bayern | F25: =+E25/D25 -> #DIV/0! | H25: - | I25: -
B26: Germany | C26: Alba Berlin | F26: =+E26/D26 -> #DIV/0! | H26: - | I26: -
B27: Germany | C27: Bamberg Baskets | F27: =+E27/D27 -> #DIV/0! | H27: - | I27: -
B28: Germany | C28: Telekom Baskets Bonn | F28: =+E28/D28 -> #DIV/0! | H28: - | I28: -
B29: Germany | C29: Wurzburg | F29: =+E29/D29 -> #DIV/0! | H29: - | I29: -
B30: Germany | C30: Ratiopharm Ulm | F30: =+E30/D30 -> #DIV/0! | H30: - | I30: -
B31: Germany | C31: Rasta Vechta | F31: =+E31/D31 -> #DIV/0! | H31: - | I31: -
B32: Germany | C32: Gladiators Trier | F32: =+E32/D32 -> #DIV/0! | H32: - | I32: -
B33: Germany | C33: Rostock Seawolves | F33: =+E33/D33 -> #DIV/0! | H33: - | I33: -
B34: Germany | C34: MHP Riesen Ludwigsburg | F34: =+E34/D34 -> #DIV/0! | H34: - | I34: -
B35: Germany | C35: EWE Baskets Oldenburg | F35: =+E35/D35 -> #DIV/0! | H35: - | I35: -
B36: Germany | C36: Niners Chemnitz | F36: =+E36/D36 -> #DIV/0! | H36: - | I36: -
... B42: Germany | C42: MLP Academics Heidelberg | F42: =+E42/D42 -> #DIV/0! | H42: - | I42: -
E43: League average | F43: =average(F25:F42) -> #DIV/0!
B45: Spanish league (liga Endesa)
B46: Nation | C46: Club | D46: Total Budget | E46: Gross salary budget | F46: Salary % from total budget | G46: Budget increase from the last season | H46: Place in the national league after the regular season | I46: Participation in European tournament | J46: Source 1 | K46: Source 2 | L46: Source 3
A47: + | B47: Spain | C47: Real Madrid | D47: 55000000 | E47: 40000000 | F47: =+E47/D47 -> 0.72727273 | G47: =(D47-'Budgets 2526'!D47)/'Budgets 2526'!D47 -> 0 | H47: - | I47: - | J47: https://cronicavasca.elespanol.com/deportes/20260910/baskonia-contara-cuarto-presupuesto-acb-millones-euros/1003742791603_0.html
A48: + | B48: Spain | C48: Valencia basket | D48: 38000000 | E48: 20000000 | F48: =+E48/D48 -> 0.52631579 | G48: =(D48-'Budgets 2526'!D48)/'Budgets 2526'!D48 -> 0.085714286 | H48: - | I48: - | J48: https://www.diariosur.es/unicaja/competencia-nunca-unicaja-20260628120526-nt.html#vca=fixed-btn&vso=rrss&vmc=tw&vli=unicaja | K48: https://www.merchanendirecto.es/presupuesto-de-record-para-unicaja/ | L48: https://cronicavasca.elespanol.com/deportes/20260910/baskonia-contara-cuarto-presupuesto-acb-millones-euros/1003742791603_0.html
B49: Spain | C49: Kosner Baskonia | D49: 23000000 | E49: 15000000 | F49: =+E49/D49 -> 0.65217391 | G49: =(D49-'Budgets 2526'!D49)/'Budgets 2526'!D49 -> 0.35294118 | H49: - | I49: - | J49: https://www.merchanendirecto.es/presupuesto-de-record-para-unicaja/ | K49: https://cronicavasca.elespanol.com/deportes/20260910/baskonia-contara-cuarto-presupuesto-acb-millones-euros/1003742791603_0.html
B50: Spain | C50: UCAM Murcia | F50: =+E50/D50 -> #DIV/0! | G50: =(D50-'Budgets 2526'!D50)/'Budgets 2526'!D50 -> -1 | H50: - | I50: -
B51: Spain | C51: Barcelona | D51: 43000000 | E51: 35000000 | F51: =+E51/D51 -> 0.81395349 | G51: =(D51-'Budgets 2526'!D51)/'Budgets 2526'!D51 -> 0.069651741 | H51: - | I51: - | J51: https://www.lesportiudecatalunya.cat/basquet/article/2659368-aposta-forta-6-5-milions-d-euros-mes.html | K51: https://cronicaglobal.elespanol.com/culemania/palco/20260321/laporta-subira-presupuesto-barca-basket-millones-temporada/1003742743992_0.html | L51: https://www.sport.es/es/noticias/barca/baloncesto/salto-dara-barca-basket-nivel-130299412
B52: Spain | C52: Joventut Badalona | F52: =+E52/D52 -> #DIV/0! | G52: =(D52-'Budgets 2526'!D52)/'Budgets 2526'!D52 -> -1 | H52: - | I52: -
B53: Spain | C53: Surne Bilbao Basket | F53: =+E53/D53 -> #DIV/0! | G53: =(D53-'Budgets 2526'!D53)/'Budgets 2526'!D53 -> -1 | H53: - | I53: -
B54: Spain | C54: Tenerife | F54: =+E54/D54 -> #DIV/0! | G54: =(D54-'Budgets 2526'!D54)/'Budgets 2526'!D54 -> -1 | H54: - | I54: -
B55: Spain | C55: Malaga Unicaja | D55: 19000000 | E55: 12500000 | F55: =+E55/D55 -> 0.65789474 | G55: =(D55-'Budgets 2526'!D55)/'Budgets 2526'!D55 -> 0.17283951 | H55: - | I55: - | J55: https://www.diariosur.es/unicaja/presupuesto-record-unicaja-baloncesto-2026-2027-20260611183146-nt.html | K55: https://www.merchanendirecto.es/presupuesto-de-record-para-unicaja/ | L55: https://cronicavasca.elespanol.com/deportes/20260910/baskonia-contara-cuarto-presupuesto-acb-millones-euros/1003742791603_0.html
B56: Spain | C56: Kids&Us Manresa | F56: =+E56/D56 -> #DIV/0! | G56: =(D56-'Budgets 2526'!D56)/'Budgets 2526'!D56 -> -1 | H56: - | I56: -
B57: Spain | C57: Rio Breogan | F57: =+E57/D57 -> #DIV/0! | G57: =(D57-'Budgets 2526'!D57)/'Budgets 2526'!D57 -> -1 | H57: - | I57: -
B58: Spain | C58: FIATC Basquet Girona | F58: =+E58/D58 -> #DIV/0! | G58: =(D58-'Budgets 2526'!D58)/'Budgets 2526'!D58 -> -1 | H58: - | I58: -
B59: Spain | C59: San Pablo Burgos | F59: =+E59/D59 -> #DIV/0! | G59: =(D59-'Budgets 2526'!D59)/'Budgets 2526'!D59 -> -1 | H59: - | I59: -
B60: Spain | C60: Ilerna Lleida | D60: 6500000 | E60: 4000000 | F60: =+E60/D60 -> 0.61538462 | G60: =(D60-'Budgets 2526'!D60)/'Budgets 2526'!D60 -> 0.083333333 | H60: - | I60: - | J60: https://www.segre.com/es/deportes/260820/empieza-reto_1308642.html
B61: Spain | C61: Casademont Zaragoza | F61: =+E61/D61 -> #DIV/0! | G61: =(D61-'Budgets 2526'!D61)/'Budgets 2526'!D61 -> -1 | H61: - | I61: -
B62: Spain | C62: MoraBanc Andorra | F62: =+E62/D62 -> #DIV/0! | G62: =(D62-'Budgets 2526'!D62)/'Budgets 2526'!D62 -> -1 | H62: - | I62: -
B63: Spain | C63: Leyma Coruna | D63: 5500000 | E63: 3250000 | F63: =+E63/D63 -> 0.59090909 | G63: =(D63-3300000)/3300000 -> 0.66666667 | H63: - | I63: - | J63: https://www.lavozdegalicia.es/noticia/basquetcoruna/2026/06/10/leyma-basquet-coruna-contara-presupuesto-5-6-millones/00031781113228571297171.htm
B64: Spain | C64: Monbus Obradoiro | D64: 4800000 | E64: 2800000 | F64: =+E64/D64 -> 0.58333333 | G64: -% | H64: - | I64: - | J64: https://www.elcorreogallego.es/deportes/2026/09/02/obradoiro-desnuda-regreso-acb-monbus-liga-endesa-diego-epifanio-epi-hector-galan-mercado-fichajes-133867789.html | M64: taxes expl
E65: League average | F65: =average(F47:F64) -> #DIV/0!
B67: Italian league (Lega A)
B68: Nation | C68: Club | D68: Total Budget | E68: Gross salary budget | F68: Salary % from total budget | G68: Budget increase from the last season | H68: Place in the national league after the regular season | I68: Participation in European tournament | J68: Source 1 | K68: Source 2 | L68: Source 3 | M68: Source 4
B69: Italy | C69: Virtus Bologna | D69: 25000000 | E69: 15000000 | F69: =+E69/D69 -> 0.6 | H69: - | I69: - | J69: https://x.com/hizlihucum/status/2070424325295890624
B70: Italy | C70: Brescia | F70: =+E70/D70 -> #DIV/0! | H70: - | I70: -
B71: Italy | C71: Olimpia Milano | F71: =+E71/D71 -> #DIV/0! | H71: - | I71: -
B72: Italy | C72: Venezia | F72: =+E72/D72 -> #DIV/0! | H72: - | I72: -
B73: Italy | C73: Tortona | F73: =+E73/D73 -> #DIV/0! | H73: - | I73: -
B74: Italy | C74: Reggiana | F74: =+E74/D74 -> #DIV/0! | H74: - | I74: -
B75: Italy | C75: Trieste | F75: =+E75/D75 -> #DIV/0! | H75: - | I75: -
B76: Italy | C76: Trento | F76: =+E76/D76 -> #DIV/0! | H76: - | I76: -
B77: Italy | C77: Varese | F77: =+E77/D77 -> #DIV/0! | H77: - | I77: -
B78: Italy | C78: Napoli | F78: =+E78/D78 -> #DIV/0! | H78: - | I78: -
B79: Italy | C79: Cremona | F79: =+E79/D79 -> #DIV/0! | H79: - | I79: -
B80: Italy | C80: Treviso | F80: =+E80/D80 -> #DIV/0! | H80: - | I80: -
B81: Italy | C81: Udine | F81: =+E81/D81 -> #DIV/0! | H81: - | I81: -
... B84: Italy | C84: Trapani | F84: =+E84/D84 -> #DIV/0! | H84: - | I84: -
E85: League average | F85: =average(F69:F84) -> #DIV/0!
B87: Lithuanian league (LKL)
B88: Nation | C88: Club | D88: Total Budget | E88: Gross salary budget | F88: Salary % from total budget | G88: Total budget increase from the last season | H88: Place in the national league after the regular season | I88: Participation in European tournament | J88: Source 1 | K88: Source 2
B89: Lithuania | C89: Žalgiris | D89: 30000000 | E89: 20000000 | F89: =+E89/D89 -> 0.66666667 | G89: =(D89-'Budgets 2526'!D89)/'Budgets 2526'!D89 -> 0.38248848 | H89: - | I89: - | J89: https://www.15min.lt/24sek/naujiena/europa/lkl-klubai-prie-starto-linijos-i-dalis-biudzetai-zvaigzdes-klaustukai-ir-prognozes-874-2527376 | K89: https://www.15min.lt/24sek/naujiena/lietuva/lkl-klubai-prie-starto-linijos-ii-dalis-rekordinis-ryto-biudzetas-ir-neptuno-potencialas-875-2525574
B90: Lithuania | C90: Rytas | D90: 10535000 | E90: 5320000 | F90: =+E90/D90 -> 0.50498339 | G90: =(D90-'Budgets 2526'!D90)/'Budgets 2526'!D90 -> 0.54155692 | H90: - | I90: - | J90: https://www.15min.lt/24sek/naujiena/europa/lkl-klubai-prie-starto-linijos-i-dalis-biudzetai-zvaigzdes-klaustukai-ir-prognozes-874-2527376 | K90: https://www.15min.lt/24sek/naujiena/lietuva/lkl-klubai-prie-starto-linijos-ii-dalis-rekordinis-ryto-biudzetas-ir-neptuno-potencialas-875-2525574
B91: Lithuania | C91: Neptūnas | D91: 3300000 | E91: 1900000 | F91: =+E91/D91 -> 0.57575758 | G91: =(D91-'Budgets 2526'!D91)/'Budgets 2526'!D91 -> 0.17857143 | H91: - | I91: - | J91: https://www.15min.lt/24sek/naujiena/europa/lkl-klubai-prie-starto-linijos-i-dalis-biudzetai-zvaigzdes-klaustukai-ir-prognozes-874-2527376 | K91: https://www.15min.lt/24sek/naujiena/lietuva/lkl-klubai-prie-starto-linijos-ii-dalis-rekordinis-ryto-biudzetas-ir-neptuno-potencialas-875-2525574
B92: Lithuania | C92: Šiauliai | D92: 2300000 | E92: 1200000 | F92: =+E92/D92 -> 0.52173913 | G92: =(D92-'Budgets 2526'!D92)/'Budgets 2526'!D92 -> 0.15 | H92: - | I92: - | J92: https://www.15min.lt/24sek/naujiena/europa/lkl-klubai-prie-starto-linijos-i-dalis-biudzetai-zvaigzdes-klaustukai-ir-prognozes-874-2527376 | K92: https://www.15min.lt/24sek/naujiena/lietuva/lkl-klubai-prie-starto-linijos-ii-dalis-rekordinis-ryto-biudzetas-ir-neptuno-potencialas-875-2525574
B93: Lithuania | C93: Lietkabelis | D93: 2600000 | E93: 1200000 | F93: =+E93/D93 -> 0.46153846 | G93: =(D93-'Budgets 2526'!D93)/'Budgets 2526'!D93 -> 0 | H93: - | I93: - | J93: https://www.15min.lt/24sek/naujiena/europa/lkl-klubai-prie-starto-linijos-i-dalis-biudzetai-zvaigzdes-klaustukai-ir-prognozes-874-2527376 | K93: https://www.15min.lt/24sek/naujiena/lietuva/lkl-klubai-prie-starto-linijos-ii-dalis-rekordinis-ryto-biudzetas-ir-neptuno-potencialas-875-2525574
B94: Lithuania | C94: Gargždai | D94: 1000000 | E94: 650000 | F94: =+E94/D94 -> 0.65 | G94: =(D94-'Budgets 2526'!D94)/'Budgets 2526'!D94 -> 0 | H94: - | I94: - | J94: https://www.15min.lt/24sek/naujiena/europa/lkl-klubai-prie-starto-linijos-i-dalis-biudzetai-zvaigzdes-klaustukai-ir-prognozes-874-2527376 | K94: https://www.15min.lt/24sek/naujiena/lietuva/lkl-klubai-prie-starto-linijos-ii-dalis-rekordinis-ryto-biudzetas-ir-neptuno-potencialas-875-2525574
B95: Lithuania | C95: Juventus | D95: 2200000 | E95: 1300000 | F95: =+E95/D95 -> 0.59090909 | G95: =(D95-'Budgets 2526'!D95)/'Budgets 2526'!D95 -> 0.375 | H95: - | I95: - | J95: https://www.15min.lt/24sek/naujiena/europa/lkl-klubai-prie-starto-linijos-i-dalis-biudzetai-zvaigzdes-klaustukai-ir-prognozes-874-2527376 | K95: https://www.15min.lt/24sek/naujiena/lietuva/lkl-klubai-prie-starto-linijos-ii-dalis-rekordinis-ryto-biudzetas-ir-neptuno-potencialas-875-2525574
B96: Lithuania | C96: Jonava | D96: 1000000 | E96: 580000 | F96: =+E96/D96 -> 0.58 | G96: =(D96-'Budgets 2526'!D96)/'Budgets 2526'!D96 -> -0.11894273 | H96: - | I96: - | J96: https://www.15min.lt/24sek/naujiena/europa/lkl-klubai-prie-starto-linijos-i-dalis-biudzetai-zvaigzdes-klaustukai-ir-prognozes-874-2527376 | K96: https://www.15min.lt/24sek/naujiena/lietuva/lkl-klubai-prie-starto-linijos-ii-dalis-rekordinis-ryto-biudzetas-ir-neptuno-potencialas-875-2525574
B97: Lithuania | C97: Nevėžis | D97: 1000000 | E97: 580000 | F97: =+E97/D97 -> 0.58 | G97: =(D97-'Budgets 2526'!D97)/'Budgets 2526'!D97 -> 0 | H97: - | I97: - | J97: https://www.15min.lt/24sek/naujiena/europa/lkl-klubai-prie-starto-linijos-i-dalis-biudzetai-zvaigzdes-klaustukai-ir-prognozes-874-2527376 | K97: https://www.15min.lt/24sek/naujiena/lietuva/lkl-klubai-prie-starto-linijos-ii-dalis-rekordinis-ryto-biudzetas-ir-neptuno-potencialas-875-2525574
B98: Lithuania | C98: Tauragė | D98: 1200000 | E98: 750000 | F98: =+E98/D98 -> 0.625 | G98: =(D98-'Budgets 2526'!D98)/'Budgets 2526'!D98 -> #DIV/0! | H98: - | I98: - | J98: https://www.15min.lt/24sek/naujiena/europa/lkl-klubai-prie-starto-linijos-i-dalis-biudzetai-zvaigzdes-klaustukai-ir-prognozes-874-2527376 | K98: https://www.15min.lt/24sek/naujiena/lietuva/lkl-klubai-prie-starto-linijos-ii-dalis-rekordinis-ryto-biudzetas-ir-neptuno-potencialas-875-2525574
E99: League average | F99: =average(F89:F97) -> 0.57017715
B101: Greek league (GBL)
B102: Nation | C102: Club | D102: Total Budget | E102: Gross salary budget | F102: Salary % from total budget | G102: Budget increase from the last season | H102: Place in the national league after the regular season | I102: Participation in European tournament | J102: Source 1
B103: Greece | C103: Olympiacos | F103: =+E103/D103 -> #DIV/0! | G103: =(D103-'Budgets 2526'!D102)/'Budgets 2526'!D102 -> -1 | H103: - | I103: -
B104: Greece | C104: Panathinaikos | D104: 60000000 | E104: 53500000 | F104: =+E104/D104 -> 0.89166667 | G104: =(D104-'Budgets 2526'!D103)/'Budgets 2526'!D103 -> 0.090909091 | H104: - | I104: - | J104: https://www.gazzetta.gr/basketball/euroleague/2552984/panathinaikos-giampoysele-o-3os-me-4-ekatommyria-symbolaio-prokalei
B105: Greece | C105: PAOK | F105: =+E105/D105 -> #DIV/0! | G105: =(D105-'Budgets 2526'!D104)/'Budgets 2526'!D104 -> -1 | H105: - | I105: -
B106: Greece | C106: AEK | F106: =+E106/D106 -> #DIV/0! | G106: =(D106-'Budgets 2526'!D105)/'Budgets 2526'!D105 -> -1 | H106: - | I106: -
B107: Greece | C107: Aris | F107: =+E107/D107 -> #DIV/0! | G107: =(D107-'Budgets 2526'!D106)/'Budgets 2526'!D106 -> -1 | H107: - | I107: -
B108: Greece | C108: Peristeri | F108: =+E108/D108 -> #DIV/0! | G108: =(D108-'Budgets 2526'!D107)/'Budgets 2526'!D107 -> -1 | H108: - | I108: -
B109: Greece | C109: Mykonos | F109: =+E109/D109 -> #DIV/0! | G109: =(D109-'Budgets 2526'!D108)/'Budgets 2526'!D108 -> -1 | H109: - | I109: -
B110: Greece | C110: Kolossos Rhodes | F110: =+E110/D110 -> #DIV/0! | G110: =(D110-'Budgets 2526'!D109)/'Budgets 2526'!D109 -> -1 | H110: - | I110: -
B111: Greece | C111: Iraklis | F111: =+E111/D111 -> #DIV/0! | G111: =(D111-'Budgets 2526'!D110)/'Budgets 2526'!D110 -> -1 | H111: - | I111: -
B112: Greece | C112: Promitheas Patras | F112: =+E112/D112 -> #DIV/0! | G112: =(D112-'Budgets 2526'!D111)/'Budgets 2526'!D111 -> -1 | H112: - | I112: -
B113: Greece | C113: Karditsas | F113: =+E113/D113 -> #DIV/0! | G113: =(D113-'Budgets 2526'!D112)/'Budgets 2526'!D112 -> -1 | H113: - | I113: -
B114: Greece | C114: Maroussi | F114: =+E114/D114 -> #DIV/0! | G114: =(D114-'Budgets 2526'!D113)/'Budgets 2526'!D113 -> -1 | H114: - | I114: -
B115: Greece | C115: Panionios | F115: =+E115/D115 -> #DIV/0! | G115: =(D115-'Budgets 2526'!D114)/'Budgets 2526'!D114 -> -1 | H115: - | I115: -
E116: League average | F116: =average(F103:F115) -> #DIV/0!
B118: Turkish league (Super Ligi)
...

Sheet Budgets 2526
B3: French league (Betclic Elite)
B4: Nation | C4: Club | D4: Total Budget | E4: Gross salary budget | F4: Salary % from total budget | G4: Place in the national league after the regular season | H4: Participation in European tournament
B5: France | C5: Paris | D5: 28883000 | E5: 7970000 | F5: =+E5/D5 -> 0.27594086 | G5: 1 | H5: Euroleague - regular season 16 place
B6: France | C6: Monaco | D6: 38715000 | E6: 20134000 | F6: =+E6/D6 -> 0.52005683 | G6: 2 | H6: Euroleague - Top 8 / quarter-finals
B7: France | C7: Nanterre | D7: 5627000 | E7: 1598000 | F7: =+E7/D7 -> 0.28398792 | G7: 3 | H7: -
B8: France | C8: Asvel | D8: 18689000 | E8: 4546000 | F8: =+E8/D8 -> 0.24324469 | G8: 4 | H8: Euroleague - regular season 20 place
B9: France | C9: Cholet | D9: 6460000 | E9: 1631000 | F9: =+E9/D9 -> 0.25247678 | G9: 5 | H9: BCL - Play-in round
B10: France | C10: Le Mans | D10: 7510000 | E10: 2282000 | F10: =+E10/D10 -> 0.30386152 | G10: 6 | H10: BCL - Top 16 round
B11: France | C11: Bourg-en-Bresse | D11: 8122000 | E11: 2300000 | F11: =+E11/D11 -> 0.28318148 | G11: 7 | H11: Eurocup - Winners
B12: France | C12: Strasbourg | D12: 7071000 | E12: 2898000 | F12: =+E12/D12 -> 0.40984302 | G12: 8 | H12: -
B13: France | C13: Chalon | D13: 7188000 | E13: 2034000 | F13: =+E13/D13 -> 0.28297162 | G13: 9 | H13: BCL - Top 16 round
B14: France | C14: Nancy | D14: 5836000 | E14: 1733000 | F14: =+E14/D14 -> 0.29694997 | G14: 10 | H14: -
B15: France | C15: Dijon | D15: 6370000 | E15: 1965000 | F15: =+E15/D15 -> 0.30847724 | G15: 11 | H15: Fiba Europe Cup - did not advance from the group to the next round
B16: France | C16: Boulazac | D16: 3853000 | E16: 1242000 | F16: =+E16/D16 -> 0.32234622 | G16: 12 | H16: -
... B20: France | C20: Le Portel | D20: 3741000 | E20: 968000 | F20: =+E20/D20 -> 0.25875434 | G20: 16 | H20: -
E21: League average | F21: =average(F5:F20) -> 0.31542792
B23: German league (easyCredit BBL)
B24: Nation | C24: Club | D24: Total Budget | E24: Gross salary budget | F24: Salary % from total budget | G24: Place in the national league after the regular season | H24: Participation in European tournament
B25: Germany | C25: FC Bayern | D25: 48420000 | E25: 18030000 | F25: =+E25/D25 -> 0.37236679 | G25: 1 | H25: Euroleague - regular season 13 place
B26: Germany | C26: Alba Berlin | D26: 11420000 | E26: 4690000 | F26: =+E26/D26 -> 0.41068301 | G26: 2 | H26: BCL- Top 8 / quarter-finals
B27: Germany | C27: Bamberg Baskets | D27: 5580000 | E27: 1460000 | F27: =+E27/D27 -> 0.26164875 | G27: 3 | H27: -
B28: Germany | C28: Telekom Baskets Bonn | D28: 9160000 | E28: 3240000 | F28: =+E28/D28 -> 0.35371179 | G28: 4 | H28: -
B29: Germany | C29: Wurzburg | D29: 6730000 | E29: 2750000 | F29: =+E29/D29 -> 0.40861813 | G29: 5 | H29: BCL - Top 16
B30: Germany | C30: Ratiopharm Ulm | D30: 9210000 | E30: 3000000 | F30: =+E30/D30 -> 0.3257329 | G30: 6 | H30: Eurocup - regular season 7 place
B31: Germany | C31: Rasta Vechta | D31: 5680000 | E31: 2460000 | F31: =+E31/D31 -> 0.43309859 | G31: 7 | H31: Fiba Europe Cup - did not advance from the group to the next round
B32: Germany | C32: Gladiators Trier | D32: 4620000 | E32: 1560000 | F32: =+E32/D32 -> 0.33766234 | G32: 8 | H32: -
B33: Germany | C33: Rostock Seawolves | D33: 7040000 | E33: 2110000 | F33: =+E33/D33 -> 0.29971591 | G33: 9 | H33: Fiba Europe Cup - Top 16
B34: Germany | C34: MHP Riesen Ludwigsburg | D34: 5740000 | E34: 2520000 | F34: =+E34/D34 -> 0.43902439 | G34: 10 | H34: -
B35: Germany | C35: EWE Baskets Oldenburg | D35: 9080000 | E35: 3170000 | F35: =+E35/D35 -> 0.34911894 | G35: 11 | H35: -
B36: Germany | C36: Niners Chemnitz | D36: 7510000 | E36: 2760000 | F36: =+E36/D36 -> 0.36750999 | G36: 12 | H36: Eurocup - 1/8 finals
... B41: Germany | C41: Lowen Braunschweig | D41: 6680000 | E41: 1860000 | F41: =+E41/D41 -> 0.27844311 | G41: 17 | H41: Fiba Europe Cup - did not advance from the group to the next round
B42: Germany | C42: MLP Academics Heidelberg | D42: 6020000 | E42: 2200000 | F42: =+E42/D42 -> 0.3654485 | G42: 18 | H42: BCL - Play-in round | P42: Unicaja - šiek tiek virš 16 mln bendras (algoms ~9-10), (penktas didžiausias ACB, prezidento žodžiai) Tenerifė - 11-12 mln. (algoms apie 6-6.5 mln) AEK- 6-7 mln (algoms 3.5-4.5 mln) Kitos komandos TOP 8: Joventut ~9 mln (Algoms apie ~6 mln) Galatasaray - 7.7 eur (5.3 mln algoms) oficialūs skaičiai Alba Berlin - 11.4 mln (4.7 mln algoms) Nymburk - ~3 mln eur (1,5-2 mln algoms) Kitos komandos TOP16: Würzburg - 6.73 mln (algoms 2.8mln. ) Gran Canaria - ~11 mln (algoms 5-5.5 mln.) Le Mans - 7.5 mln (algoms 2.3 mln) Chalon - 7.2 mln (algoms 2 mln.) Trieste - 6-7.5 mln (algoms 3,5-4,5 mln) Tofaš - 6-8 mln. (algoms 4-5.5 mln) Holon - 4.5-6 mln (algoms 3-4 mln) Karditsas- 2.5-4 mln (algoms 1.5-2.5 mln) Rytas -6.6 mln (algoms 3.2 mln)
E43: League average | F43: =average(F25:F42) -> 0.35279557
B45: Spanish league (liga Endesa)
B46: Nation | C46: Club | D46: Total Budget | E46: Gross salary budget | F46: Salary % from total budget | G46: Place in the national league after the regular season | H46: Participation in European tournament | I46: Source 1 | J46: Source 2 | K46: Source 3
A47: + | B47: Spain | C47: Real Madrid | D47: 55000000 | E47: 34300000 | F47: =+E47/D47 -> 0.62363636 | G47: 1 | H47: Euroleague - F4 / second place | I47: https://www.2playbook.com/clubes/real-madrid-perdera-38-millones-con-baloncesto-en-2025-2026-como-paso-previo-su-apuesta-nba_20577_102.html | J47: https://encestando.es/el-real-madrid-facturo-25-millones-la-pasada-temporada-y-perdio-195-este-ano-preve-38 | K47: https://cronicaglobal.elespanol.com/culemania/palco/20251115/barca-basket-millones-real-madrid-jugadores-laporta/1003742707818_0.html
A48: + | B48: Spain | C48: Valencia | D48: 35000000 | E48: 19000000 | F48: =+E48/D48 -> 0.54285714 | G48: 2 | H48: Euroleague - F4 / semi-finals | I48: https://as.com/baloncesto/el-bilbao-basket-empieza-a-crecer-f202512-n/ | J48: https://www.basketeurope.com/euroleague-valence-booste-son-budget-a-35-millions-deuros/ | K48: https://www.lasprovincias.es/deportes/valencia-bc/valencia-basket-aprueba-presupuesto-record-millones-temporada-20251211191149-nt.html
B49: Spain | C49: Baskonia | D49: 17000000 | E49: 12000000 | F49: =+E49/D49 -> 0.70588235 | G49: 3 | H49: Euroleague - regular season 18 place | I49: https://cronicavasca.elespanol.com/deportes/20250727/baskonia-seguira-potente-acb-contara-millones-presupuesto/1003742675823_0.html | J49: https://www.elcorreo.com/baskonia/baskonia-pablo-laso-costo-113-millones-euros-20251130000753-nt.html | K49: https://cronicavasca.elespanol.com/deportes/20260227/baskonia-cuarto-presupuesto-salarial-euroliga-millones-euros/1003742736078_0.html
B50: Spain | C50: UCAM Murcia | D50: 6000000 | E50: 3900000 | F50: =+E50/D50 -> 0.65 | G50: 4 | H50: Fiba Europe Cup - F4 / semi-finals | I50: https://www.marca.com/baloncesto/acb/playoffs/2024/06/06/665de632268e3e39178b4602.html | J50: https://cadenaser.com/murcia/2025/05/14/alejandro-gomez-presupuesto-de-ucam-murcia-y-planificacion-de-la-proxima-temporada-radio-murcia/ | K50: https://palco23.mundodeportivo.com/clubes/ucam-murcia-refuerza-su-estructura-con-una-ampliacion-de-capital-de-970000-euros
B51: Spain | C51: Barcelona | D51: 40200000 | E51: 29250000 | F51: =+E51/D51 -> 0.72761194 | G51: 5 | H51: Euroleague - play-in round | I51: https://www.eurohoops.net/en/euroleague/1941681/joan-laporta-talks-budget-barcelona-euroleague/ | J51: -
B52: Spain | C52: Joventut Badalona | D52: 9000000 | E52: 6000000 | F52: =+E52/D52 -> 0.66666667 | G52: 6 | H52: BCL- Top 8 / quarter-finals | I52: https://www.2playbook.com/clubes/joventut-badalona-formaliza-ampliacion-capital-717685-euros_17599_102.html | J52: https://palco23.mundodeportivo.com/clubes/joventut-de-badalona-perdio-46-millones-en-un-complicado-2023-2024 | K52: https://palco23.mundodeportivo.com/clubes/joventut-de-badalona-engorda-su-agujero-pese-a-recortar-casi-un-30-sus-perdidas-en-2024-2025
B53: Spain | C53: Bibao Basket | D53: 5400000 | E53: 2392576 | F53: =+E53/D53 -> 0.44306963 | G53: 7 | H53: Fiba Europe Cup - Winner | I53: https://www.naiz.eus/info/noticia/20251230/bilbao-basket-aprueba-un-presupuesto-de-5-4-millones-de-euros-para-cerrar-un-curso-historico | J53: https://radiopopular.com/2025/12/el-bilbao-basket-pasa-de-resistir-a-construir-futuro | K53: https://www.elcorreo.com/bilbaobasket/surne-bilbao-fija-presupuesto-millones-destina-brutos-20251229212548-nt.html?ref=https%3A%2F%2Fwww.elcorreo.com%2Fbilbaobasket%2Fsurne-bilbao-fija-presupuesto-millones-destina-brutos-20251229212548-nt.html
B54: Spain | C54: Tenerife | D54: 10700000 | E54: 7800000 | F54: =+E54/D54 -> 0.72897196 | G54: 8 | H54: BCL - F4 / fourth place | I54: https://www.eldia.es/deportes/cb-canarias/2026/01/19/canarias-cierra-pasado-ejercicio-200-125859060.html | J54: https://www.2playbook.com/clubes/laguna-tenerife-cierra-en-beneficios-factura-114-millones-euros-en-2024-2025_21196_102.html
B55: Spain | C55: Unicaja | D55: 16200000 | E55: 11000000 | F55: =+E55/D55 -> 0.67901235 | G55: 9 | H55: BCL - F4 / third place | I55: https://www.malagahoy.es/unicaja/presupuestos-euroliga-24-25-estaria-unicaja_0_2003407564.html | J55: https://www.malagahoy.es/unicaja/estaria-unicaja-ranking-gasto-neto_0_2005999254.html
B56: Spain | C56: Baxi Manresa | D56: 4100000 | E56: 2800000 | F56: =+E56/D56 -> 0.68292683 | G56: 10 | H56: Eurocup - 1/8 finals | I56: https://palco23.mundodeportivo.com/clubes/baxi-manresa-busca-la-permanencia-con-41-millones-de-presupuesto-en-2025-2026 | J56: -
B57: Spain | C57: Rio Breogan | D57: 4500000 | E57: 3025000 | F57: =+E57/D57 -> 0.67222222 | G57: 11 | H57: - | I57: https://www.cbbreogan.com/jgo/INFORME_DE_GESTION_24_25.pdf | J57: https://www.2playbook.com/clubes/rio-breogan-cierra-2023-2024-con-beneficio-600000-euros-presupuesta-417-millones_17233_102.html
B58: Spain | C58: Basquet Girona | D58: 4200000 | E58: 2400000 | F58: =+E58/D58 -> 0.57142857 | G58: 12 | H58: - | I58: https://www.2playbook.com/clubes/marc-gasol-inyectara-24-millones-en-basquet-girona-convertir-club-en-sad_14882_102.html | J58: https://palco23.mundodeportivo.com/clubes/basquet-girona-objetivo-cumplido-en-2022-2023-con-hasta-cuatro-millones-de-presupuesto
B59: Spain | C59: San Pablo Burgos | D59: 4200000 | E59: 2600000 | F59: =+E59/D59 -> 0.61904762 | G59: 13 | H59: - | I59: - | J59: -
B60: Spain | C60: Lleida | D60: 6000000 | E60: 3500000 | F60: =+E60/D60 -> 0.58333333 | G60: 14 | H60: - | I60: https://diaricatalunya.cat/es/segria/lleida/el-forca-lleida-roza-los-seis-millones-de-euros-de-presupuesto-cifra-record | J60: https://www.segre.com/es/opinion/editorial/250802/el-gran-coste-de-competir-en-la-elite-deportiva_913619.html
B61: Spain | C61: Casademont Zaragoza | D61: 3900000 | E61: 2500000 | F61: =+E61/D61 -> 0.64102564 | G61: 15 | H61: Fiba Europe Cup - Top 16 | I61: https://foros.acb.com/forum/index.php?thread/521107-casademont-zaragoza-2025-2026-confiamos-en-plaza-si-se-puede/&postID=33965944 | J61: -
B62: Spain | C62: Andorra | D62: 5900000 | E62: 3500000 | F62: =+E62/D62 -> 0.59322034 | G62: 16 | H62: - | I62: https://www.bca.ad/es/el-bc-morabanc-andorra-reafirma-su-solidez-economica-y-su-compromiso-con-la-transparencia/ | J62: -
B63: Spain | C63: CB Gran Canaria | D63: 10800000 | E63: 6200000 | F63: =+E63/D63 -> 0.57407407 | G63: 17 | H63: BCL - Top 16 | I63: https://www.atlanticohoy.com/deportes-sa/cb-gran-canaria-aprueba-presupuesto-103-millones-mitad-procede-erario-publico_1538123_102.html | J63: -
B64: Spain | C64: Granada | D64: 4650000 | E64: 2100000 | F64: =+E64/D64 -> 0.4516129 | G64: 18 | H64: - | I64: https://www.ideal.es/deportes/fundacioncbgranada/coviran-invierte-poco-dos-millones-euros-jugadores-20251022095748-nt.html?ref=https%3A%2F%2Fwww.ideal.es%2Fdeportes%2Ffundacioncbgranada%2Fcoviran-invierte-poco-dos-millones-euros-jugadores-20251022095748-nt.html | J64: - | K64: https://www.basketnews.lt/news-180219-brangiausiu-eurolygos-zaideju-penkioliktukas.html | L64: taxes expl
E65: League average | F65: =average(F47:F64) -> 0.61981111
B67: Italian league (Lega A)
B68: Nation | C68: Club | D68: Total Budget | E68: Gross salary budget | F68: Salary % from total budget | G68: Place in the national league after the regular season | H68: Participation in European tournament | I68: Source 1 | J68: Source 2 | K68: Source 3 | L68: Source 4
B69: Italy | C69: Virtus Bologna | D69: 21000000 | E69: 13300000 | F69: =+E69/D69 -> 0.63333333 | G69: 1 | H69: Euroleague - regular season 17 place | I69: https://basketnews.com/news-204932-euroleague-teams-clubs-budgets.html | J69: https://www.sportefinanza.it/2025/12/06/virtus-bologna-bilancio-perdita-zanetti/ | K69: https://basketnews.com/news-233398-euroleague-budgets-payrolls-2026-biggest-spenders.html | L69: https://www.reportaziende.it/virtus_pallacanestro_bologna_societa_per_azioni_bo_00584700371
B70: Italy | C70: Brescia | D70: =9090000 -> 9090000 | E70: 4600000 | F70: =+E70/D70 -> 0.50605061 | G70: 2 | H70: - | I70: https://www.ufficiocamerale.it/3138/pallacanestro-brescia-srl#:~:text=Indirizzo%3A%20VIA%20CAPRERA%205%20%2D%2025125,Dipendenti%20%3A%2021%20(2026) | J70: https://www.reportaziende.it/pallacanestro_brescia_srl_bs_02800370989 | K70: https://obiettivolavoro.it/stipendi-basket-serie-a-quanto-guadagnano-i-giocatori-cestisti/ | L70: -
B71: Italy | C71: Olimpia Milano | D71: 40511000 | E71: 22500000 | F71: =+E71/D71 -> 0.5554047 | G71: 3 | H71: Euroleague - regular season 14 place | I71: https://realolimpiamilano.com/2025/06/10/bilancio-olimpia-milano-2024-22-3-milioni-in-salari-e-stipendi/?utm_source=chatgpt.com | J71: https://basketnews.com/news-233398-euroleague-budgets-payrolls-2026-biggest-spenders.html | K71: https://basketnews.com/news-204932-euroleague-teams-clubs-budgets.html | L71: https://www.reportaziende.it/pallacanestro_olimpia_milano_societa_sportiva_a_responsabilita_limitata_o_pallacanestro_ol_mi_01852920154
B72: Italy | C72: Venezia | D72: 12000000 | E72: 7800000 | F72: =+E72/D72 -> 0.65 | G72: 4 | H72: Eurocup - 1/8 finals | I72: https://sport.888casino.it/blog/stipendi-venezia-basket | J72: https://www.reportaziende.it/societa_sportiva_professionistica_reyer_venezia_mestre_srl_in_sigla_ssp_reyer_venezi_ve_03849670272 | K72: https://www.pianetabasket.com/olimpia-milano/lera-armani-vale-253-milioni-i-conti-di-olimpia-milano-nellanno-del-triplete | L72: -
B73: Italy | C73: Tortona | D73: 13100000 | E73: 8000000 | F73: =+E73/D73 -> 0.61068702 | G73: 5 | H73: - | I73: https://www.gazzetta.it/Basket/SerieA/16-01-2026/basket-tortona-e-il-report-semestrale-il-palasport-i-partner-la-visione-il-territorio.shtml | J73: https://www.reportaziende.it/derthona_basket_societa_sportiva_a_responsabilita_limitata_al_02224170064 | K73: - | L73: -
B74: Italy | C74: Reggiana | D74: 8690000 | E74: 3550000 | F74: =+E74/D74 -> 0.40851554 | G74: 6 | H74: Fiba Europe Cup - quarter-finals (Top 8) | I74: https://www.reportaziende.it/pallacanestro_reggiana_srl_re_00532610359 | J74: - | K74: - | L74: -
B75: Italy | C75: Trieste | D75: 9450000 | E75: 3800000 | F75: =+E75/D75 -> 0.4021164 | G75: 7 | H75: BCL - Top 16 | I75: https://www.reportaziende.it/pallacanestro_trieste_2004_societa_sportiva_dilettantistica_srl_ts_01072900325 | J75: - | K75: - | L75: -
B76: Italy | C76: Trento | D76: 6350000 | E76: 2650000 | F76: =+E76/D76 -> 0.41732283 | G76: 8 | H76: Eurocup -quarter-finals (Top 8) | I76: https://www.backdoorpodcast.com/virtus-rosso-da-euroleague-trento-e-venezia-bilanci-lba/ | J76: https://www.reportaziende.it/aquila_basket_trento_2013_srl_tn_02125690228 | K76: - | L76: -
B77: Italy | C77: Varese | D77: 6880000 | E77: 2550000 | F77: =+E77/D77 -> 0.37063953 | G77: 9 | H77: - | I77: https://sportando.basketball/openjobmetis-varese-redbird-budget-25-milioni/#goog_rewarded | J77: https://www.reportaziende.it/pallacanestro_varese_srl_va_00338980121 | K77: - | L77: -
B78: Italy | C78: Napoli | D78: 9080000 | E78: 3150000 | F78: =+E78/D78 -> 0.3469163 | G78: 10 | H78: - | I78: https://www.reportaziende.it/ss_napolibasket_srl_na_07000361217 | J78: - | K78: - | L78: -
B79: Italy | C79: Cremona | D79: 4140000 | E79: 1700000 | F79: =+E79/D79 -> 0.41062802 | G79: 11 | H79: - | I79: https://www.reportaziende.it/guerino_vanoli_basket_societa_a_responsabilita_limitata_cr_01192650198 | J79: - | K79: - | L79: -
B80: Italy | C80: Treviso | D80: 5395000 | E80: 2550000 | F80: =+E80/D80 -> 0.47265987 | G80: 12 | H80: - | I80: https://www.reportaziende.it/universo_treviso_basket_srl_tv_07362590726 | J80: - | K80: - | L80: -
B81: Italy | C81: Udine | D81: 4350000 | E81: 2050000 | F81: =+E81/D81 -> 0.47126437 | G81: 13 | H81: - | I81: https://www.reportaziende.it/amici_pallacanestro_udinese_societa_sportiva_dilettantistica_a_responsabilita_limitata_ud_02665760308 | J81: https://www.messaggeroveneto.it/sport/ap-la-forza-sono-le-idee-in-serie-a-con-un-budget-di-fascia-medio-bassa-prlv26jt | K81: - | L81: -
B82: Italy | C82: Cantu | D82: 4676000 | E82: 2350000 | F82: =+E82/D82 -> 0.5025663 | G82: 14 | H82: - | I82: https://www.reportaziende.it/pallacanestro_cantu_spa_societa_sportiva_dilettantistica_co_00254400138 | J82: - | K82: - | L82: -
... B84: Italy | C84: Trapani | D84: 7000000 | E84: 3400000 | F84: =+E84/D84 -> 0.48571429 | G84: 16 | H84: BCL - Play-in round | I84: https://www.reportaziende.it/trapani_shark_ssd_a_rl_tp_02539490819 | J84: - | K84: - | L84: -
E85: League average | F85: =average(F69:F84) -> 0.47588684
B87: Lithuanian league (LKL)
B88: Nation | C88: Club | D88: Total Budget | E88: Gross salary budget | F88: Salary % from total budget | G88: Place in the national league after the regular season | H88: Participation in European tournament | I88: Source 1 | J88: Source 2
B89: Lithuania | C89: Žalgiris | D89: 21700000 | E89: 14400000 | F89: =+E89/D89 -> 0.66359447 | G89: 1 | H89: Euroleague - Top 8 / quarter-finals | I89: https://www.lrt.lt/naujienos/sportas/10/2700152/kauno-zalgiris-pristate-rekordini-2025-2026-m-sezono-biudzeta?srsltid=AfmBOopGXyxC169tMhv2TU5SXOKXuuENL1itZs6SqKyjpXQEabWp8QfG
B90: Lithuania | C90: Rytas | D90: 6834000 | E90: 3211000 | F90: =+E90/D90 -> 0.4698566 | G90: 2 | H90: BCL - Winner | I90: https://www.delfi.lt/krepsinis/naujienos/rytas-pristate-rekordini-biudzeta-sieks-beveik-7-milijonus-euru-120178053 | J90: https://www.lrt.lt/naujienos/sportas/10/2942193/ryto-vadovas-giga-tikisi-kad-ateityje-klubo-biudzetas-sieks-20-mln-euru#:~:text=Gigos%20teigimu%2C%20klubo%20biud%C5%BEetas%20%C5%A1%C4%AF,tur%C4%97t%C5%B3%20pasiekti%209%20mln.%20eur%C5%B3.
B91: Lithuania | C91: Neptūnas | D91: 2800000 | E91: 1220000 | F91: =+E91/D91 -> 0.43571429 | G91: 3 | H91: Eurocup - regular season 8 place | I91: https://www.basketnews.lt/news-230665-neptunas-pristate-padidejusi-biudzeta-ir-skiriama-suma-krepsininkams.html
B92: Lithuania | C92: Šiauliai | D92: 2000000 | E92: 1100000 | F92: =+E92/D92 -> 0.55 | G92: 4 | H92: - | I92: https://www.15min.lt/24sek/naujiena/europa/lkl-klubai-prie-starto-linijos-i-dalis-biudzetai-zvaigzdes-klaustukai-ir-prognozes-874-2527376 | J92: https://www.15min.lt/24sek/naujiena/lietuva/po-kosmarisko-siauliu-starto-direktoriaus-zinute-pazadas-ir-atskleistas-biudzetas-875-2142054
B93: Lithuania | C93: Lietkabelis | D93: 2600000 | E93: 1200000 | F93: =+E93/D93 -> 0.46153846 | G93: 5 | H93: Eurocup - regular season 9 place | I93: https://www.basketnews.lt/news-243778-panevezys-9-tukst-euru-padidino-lietkabelio-finansavima.html#google_vignette | J93: https://www.15min.lt/24sek/naujiena/lietuva/maciulis-apie-lietkabelio-sudeti-tikslus-biudzeta-ir-isgaravusia-baime-del-canako-875-2501070
B94: Lithuania | C94: Gargždai | D94: 1000000 | E94: 700000 | F94: =+E94/D94 -> 0.7 | G94: 6 | H94: - | I94: https://www.15min.lt/24sek/naujiena/europa/lkl-klubai-prie-starto-linijos-i-dalis-biudzetai-zvaigzdes-klaustukai-ir-prognozes-874-2527376
B95: Lithuania | C95: Juventus | D95: 1600000 | E95: 950000 | F95: =+E95/D95 -> 0.59375 | G95: 7 | H95: - | I95: https://www.15min.lt/24sek/naujiena/europa/lkl-klubai-prie-starto-linijos-i-dalis-biudzetai-zvaigzdes-klaustukai-ir-prognozes-874-2527376
B96: Lithuania | C96: Jonava | D96: 1135000 | E96: 666863 | F96: =+E96/D96 -> 0.58754449 | G96: 8 | H96: - | I96: https://www.basketnews.lt/news-246157-jonavos-biudzetas-augantis-bet-ne-zaidejams.html#google_vignette
B97: Lithuania | C97: Nevėžis | D97: 1000000 | E97: 540000 | F97: =+E97/D97 -> 0.54 | G97: 9 | H97: - | I97: https://www.15min.lt/24sek/naujiena/europa/lkl-klubai-prie-starto-linijos-i-dalis-biudzetai-zvaigzdes-klaustukai-ir-prognozes-874-2527376 | J97: https://www.basketnews.lt/news-231646-nevezis-atskleide-biudzeta-desimtadalis-skolu-grazinimui.html
E98: League average | F98: =average(F89:F97) -> 0.55577759
B100: Greek league (GBL)
B101: Nation | C101: Club | D101: Total Budget | E101: Gross salary budget | F101: Salary % from total budget | G101: Place in the national league after the regular season | H101: Participation in European tournament | I101: Source 1
B102: Greece | C102: Olympiacos | D102: 45000000 | E102: 30205330 | F102: =+E102/D102 -> 0.67122956 | G102: 1 | H102: Euroleague - Winner | I102: https://basketnews.com/news-233398-euroleague-budgets-payrolls-2026-biggest-spenders.html | J102: https://www.foxbet.gr/315873/mpatzet-omadon-mpasket-a1 | K102: https://www.sport24.gr/basket/euroleague-basketball/olimpiakos-i-pio-akrivi-omada-olon-ton-epoxon-afta-einai-ta-xrisa-simvolaia-ton-erithrolefkon/
B103: Greece | C103: Panathinaikos | D103: 55000000 | E103: 37217761 | F103: =+E103/D103 -> 0.67668656 | G103: 2 | H103: Euroleague - Top 8 / quarter-finals | I103: https://as.com/baloncesto/euroliga/el-panathinaikos-el-que-mas-gasta-en-la-euroliga-f202602-n | J103: https://www.foxbet.gr/315873/mpatzet-omadon-mpasket-a1 | K103: https://www.sport24.gr/basket/euroleague-basketball/panathinaikos-aktor-i-axia-ton-prasinon-simvolaion-apogeiothike-kai-angizei-ta-25-ekatommiria/ | L103: https://www.protothema.gr/sports/article/1772720/panathinaikos-to-muthiko-sumvolaio-pou-tha-parei-heiz-devis-stin-ellada-den-xepernaei-to-kase-tou-nan/
B104: Greece | C104: PAOK | D104: 6000000 | E104: 4000000 | F104: =+E104/D104 -> 0.66666667 | G104: 3 | H104: Fiba Europe Cup - Final (second place) | I104: https://www.gazzetta.gr/basketball/basket-league/2454961/aris-me-ena-smparo-dyo-trygonia-se-protathlima-kai-euroleague | J104: https://www.foxbet.gr/315873/mpatzet-omadon-mpasket-a1
B105: Greece | C105: AEK | D105: 6000000 | E105: 3800000 | F105: =+E105/D105 -> 0.63333333 | G105: 4 | H105: BCL - F4 / Final (second place) | I105: https://www.gazzetta.gr/basketball/basket-league/2454961/aris-me-ena-smparo-dyo-trygonia-se-protathlima-kai-euroleague | J105: https://www.foxbet.gr/315873/mpatzet-omadon-mpasket-a1 | K105: https://www.superbasket.gr/basket-league/115461-angelopoulos-prin-tria-chronia-me-eiche-plesiasei-fund-gia-na-agorasei-tis-metoches-tes-aek.html
B106: Greece | C106: Aris | D106: 6500000 | E106: 4000000 | F106: =+E106/D106 -> 0.61538462 | G106: 5 | H106: Eurocup - regular season 7 place | I106: https://www.gazzetta.gr/basketball/basket-league/2454961/aris-me-ena-smparo-dyo-trygonia-se-protathlima-kai-euroleague | J106: https://www.foxbet.gr/315873/mpatzet-omadon-mpasket-a1 | K106: https://www.gazzetta.gr/basketball/eurocup/2454951/aris-sta-25-ekatommyria-eyro-o-proypologismos-tis-neas-sezon
B107: Greece | C107: Peristeri | D107: 2200000 | E107: 1380000 | F107: =+E107/D107 -> 0.62727273 | G107: 6 | H107: Fiba Europe Cup - Top 8 / quarter-finals | I107: https://www.gazzetta.gr/basketball/basket-league/2454961/aris-me-ena-smparo-dyo-trygonia-se-protathlima-kai-euroleague | J107: https://www.foxbet.gr/315873/mpatzet-omadon-mpasket-a1 | K107: https://www.sport24.gr/basket/oloi-oi-anthropoi-tou-spanouli-sto-peristeri-to-batzet-to-simvolaio-kai-oi-metagrafes/
B108: Greece | C108: Mykonos | D108: 2000000 | E108: 1380000 | F108: =+E108/D108 -> 0.69 | G108: 7 | H108: - | I108: https://www.gazzetta.gr/basketball/basket-league/2454961/aris-me-ena-smparo-dyo-trygonia-se-protathlima-kai-euroleague | J108: https://www.foxbet.gr/315873/mpatzet-omadon-mpasket-a1
B109: Greece | C109: Kolossos Rhodes | D109: 2200000 | E109: 1500000 | F109: =+E109/D109 -> 0.68181818 | G109: 8 | H109: - | I109: https://www.gazzetta.gr/basketball/basket-league/2454961/aris-me-ena-smparo-dyo-trygonia-se-protathlima-kai-euroleague | J109: https://www.foxbet.gr/315873/mpatzet-omadon-mpasket-a1
B110: Greece | C110: Iraklis | D110: 2200000 | E110: 1400000 | F110: =+E110/D110 -> 0.63636364 | G110: 9 | H110: ENBL - Top 8 / quarter-finals | I110: https://www.gazzetta.gr/basketball/basket-league/2454961/aris-me-ena-smparo-dyo-trygonia-se-protathlima-kai-euroleague | J110: https://www.foxbet.gr/315873/mpatzet-omadon-mpasket-a1
B111: Greece | C111: Promitheas Patras | D111: 2500000 | E111: 1600000 | F111: =+E111/D111 -> 0.64 | G111: 10 | H111: BCL - Play-in round | I111: https://www.gazzetta.gr/basketball/basket-league/2454961/aris-me-ena-smparo-dyo-trygonia-se-protathlima-kai-euroleague | J111: https://www.foxbet.gr/315873/mpatzet-omadon-mpasket-a1 | K111: https://www.sdna.gr/mpasket/1425204_promitheas-i-heiroteri-hronia-tis-istorias-toy-bathmologika-agonistika-dioikitika | L111: https://www.sdna.gr/mpasket/976562_o-promitheas-dilose-proypologismo-800000-ston-esake-eno-eurocup-apaitei-25
B112: Greece | C112: Karditsas | D112: 1500000 | E112: 1000000 | F112: =+E112/D112 -> 0.66666667 | G112: 11 | H112: BCL - Top 16 | I112: https://www.gazzetta.gr/basketball/basket-league/2454961/aris-me-ena-smparo-dyo-trygonia-se-protathlima-kai-euroleague | J112: https://www.foxbet.gr/315873/mpatzet-omadon-mpasket-a1
B113: Greece | C113: Maroussi | D113: 3200000 | E113: 2300000 | F113: =+E113/D113 -> 0.71875 | G113: 12 | H113: - | I113: https://www.gazzetta.gr/basketball/basket-league/2454961/aris-me-ena-smparo-dyo-trygonia-se-protathlima-kai-euroleague | J113: https://www.foxbet.gr/315873/mpatzet-omadon-mpasket-a1
B114: Greece | C114: Panionios | D114: 4000000 | E114: 2700000 | F114: =+E114/D114 -> 0.675 | G114: 13 | H114: Eurocup - regular season 10 place | I114: https://www.gazzetta.gr/basketball/basket-league/2454961/aris-me-ena-smparo-dyo-trygonia-se-protathlima-kai-euroleague | J114: https://www.foxbet.gr/315873/mpatzet-omadon-mpasket-a1 | K114: https://www.enwsi.gr/1682640/aek/aek-basket/ta-mpatzet-toy-antagonismoy-tha-anevoyn-simantika-kai-i-aek-tha-prepei-na-einai-etoimi.html
E115: League average | F115: =average(F102:F114) -> 0.66147477
...

Sheet World 2526
B3: World
B4: Nation | C4: Club | D4: Total Budget | E4: Gross salary budget | F4: Salary % from total budget | G4: Place in the national league after the regular season | H4: Participation in European tournament
B5: Latvia | C5: Latvijas Universitātes | D5: 100000 | E5: 70000 | F5: =+E5/D5 -> 0.7 | G5: 13 | H5: -
B6: Finland | C6: Korihait | D6: 345000 | E6: 203500 | F6: =+E6/D6 -> 0.58985507 | G6: 4 | H6: -
B7: Latvia | C7: Liepaja | D7: 400000 | E7: 250000 | F7: =+E7/D7 -> 0.625 | G7: 11 | H7: -
B8: Finland | C8: Bisons Laimaa | D8: 325800 | E8: 255000 | F8: =+E8/D8 -> 0.78268877 | G8: 9 | H8: -
B9: Finland | C9: Tampereen Pyrinto | D9: 402900 | E9: 275900 | F9: =+E9/D9 -> 0.68478531 | G9: 8 | H9: -
B10: Finland | C10: Kouvot | D10: 611800 | E10: 287000 | F10: =+E10/D10 -> 0.46910755 | G10: 11 | H10: -
B11: Finland | C11: Kobrat | D11: 352000 | E11: 305000 | F11: =+E11/D11 -> 0.86647727 | G11: 12 | H11: -
B12: Finland | C12: KTP Basket | D12: 442500 | E12: 307500 | F12: =+E12/D12 -> 0.69491525 | G12: 3 | H12: -
B13: Finland | C13: Tampiolan Honka | D13: 340000 | E13: 313300 | F13: =+E13/D13 -> 0.92147059 | G13: 5 | H13: -
B14: Latvia | C14: Ogre | D14: 550000 | E14: 350000 | F14: =+E14/D14 -> 0.63636364 | G14: 9 | H14: -
B15: Czech Republic | C15: Basket Brno | D15: 587238.02 | E15: 400000 | F15: =+E15/D15 -> 0.68115481 | G15: 3 | H15: Fiba Europe Cup - did not advance from the group to the next round
B16: Latvia | C16: Ventspilis | D16: 650000 | E16: 400000 | F16: =+E16/D16 -> 0.61538462 | G16: 7 | H16: -
... B22: Finland | C22: Kauhajoki | D22: 816000 | E22: 514000 | F22: =+E22/D22 -> 0.62990196 | G22: 2 | H22: -
B23: Finland | C23: BC Nokia | D23: 761500 | E23: 515000 | F23: =+E23/D23 -> 0.67629678 | G23: - | H23: -
B24: Lithuania | C24: Nevėžis | D24: 1000000 | E24: 540000 | F24: =+E24/D24 -> 0.54 | G24: 9 | H24: -
B25: Latvia | C25: Riga Zelli | D25: 950000 | E25: 560000 | F25: =+E25/D25 -> 0.58947368 | G25: 5 | H25: ENBL - Top 8 / quarter-finals
B26: Latvia | C26: Valmiera Glass/ViA | D26: 1100000 | E26: 600000 | F26: =+E26/D26 -> 0.54545455 | G26: 3 | H26: ENBL - Top 16
B27: Poland | C27: Miasto Szkła Krosno | D27: 941620.8 | E27: 600000 | F27: =+E27/D27 -> 0.63719918 | G27: 16 | H27: -
B28: Slovenia | C28: Perspektiva Illirija | D28: 957423 | E28: 600000 | F28: =+E28/D28 -> 0.62668225 | G28: 14 | H28: -
B29: Finland | C29: Helsinki Seagulls | D29: 1142200 | E29: 600800 | F29: =+E29/D29 -> 0.52600245 | G29: 6 | H29: -
B30: Hungary | C30: Alba-Fehervar | D30: 930292.38 | E30: 650000 | F30: =+E30/D30 -> 0.69870507 | G30: 5 | H30: -
B31: Montenegro | C31: Studentski Centar Derby | D31: 1000000 | E31: 650000 | F31: =+E31/D31 -> 0.65 | G31: 15 | H31: -
B32: Serbia | C32: Borac Mozzart | D32: 1000000 | E32: 650000 | F32: =+E32/D32 -> 0.65 | G32: 17 | H32: -
B33: Estonia | C33: Tartu Ulikool | D33: 1200000 | E33: 650000 | F33: =+E33/D33 -> 0.54166667 | G33: 1 | H33: Fiba Europe Cup - did not advance from the group to the next round
B34: Lithuania | C34: Jonava | D34: 1135000 | E34: 666863 | F34: =+E34/D34 -> 0.58754449 | G34: 8 | H34: -
B35: Latvia | C35: Vef Riga | D35: 1500000 | E35: 675000 | F35: =+E35/D35 -> 0.45 | G35: 2 | H35: BCL - did not advance from the group to the next round
... B40: Romania | C40: CS Vâlcea 1924 | D40: 1650000 | E40: 1000000 | F40: =+E40/D40 -> 0.60606061 | G40: 9 | H40: Fiba Europe Cup - did not advance from the group to the next round
B41: Greece | C41: Karditsas | D41: 1500000 | E41: 1000000 | F41: =E41/D41 -> 0.66666667 | G41: 11 | H41: BCL - Top 16
B42: Hungary | C42: Kaposvari | D42: 1726451 | E42: 1100000 | F42: =+E42/D42 -> 0.63714522 | G42: 3 | H42: -
B43: Lithuania | C43: Šiauliai | D43: 2000000 | E43: 1100000 | F43: =+E43/D43 -> 0.55 | G43: 4 | H43: -
B44: Poland | C44: King Wilki Morskie Szczecin | D44: 1765539 | E44: 1100000 | F44: =+E44/D44 -> 0.6230392 | G44: 2 | H44: -
B45: Romania | C45: CS Dinamo Bucharest | D45: 1800000 | E45: 1100000 | F45: =+E45/D45 -> 0.61111111 | G45: 2 | H45: -
B46: Lithuania | C46: Lietkabelis | D46: 2600000 | E46: 1200000 | F46: =+E46/D46 -> 0.46153846 | G46: 5 | H46: Eurocup - regular season 9 place
B47: Poland | C47: Trefl Sopot | D47: 1900000 | E47: 1200000 | F47: =+E47/D47 -> 0.63157895 | G47: 4 | H47: Fiba Europe Cup - Top 16
B48: Serbia | C48: FMP Beograd | D48: 1850000 | E48: 1200000 | F48: =+E48/D48 -> 0.64864865 | G48: 12 | H48: -
B49: Lithuania | C49: Neptūnas | D49: 2800000 | E49: 1220000 | F49: =+E49/D49 -> 0.43571429 | G49: 3 | H49: Eurocup - regular season 8 place
B50: France | C50: Boulazac | D50: 3853000 | E50: 1242000 | F50: =+E50/D50 -> 0.32234622 | G50: 12 | H50: -
B51: Czech Republic | C51: Era Nymburk | D51: 2000000 | E51: 1300000 | F51: =+E51/D51 -> 0.65 | G51: 1 | H51: BCL - Top 8 / quarter-finals
B52: Poland | C52: Dziki Warszawa | D52: 2000944.2 | E52: 1300000 | F52: =+E52/D52 -> 0.64969328 | G52: 5 | H52: ENBL - Winner
B53: Serbia | C53: Mega Basket | D53: 2000000 | E53: 1300000 | F53: =+E53/D53 -> 0.65 | G53: 11 | H53: -
... B55: Croatia | C55: Zadar | D55: 3034805 | E55: 1360000 | F55: =+E55/D55 -> 0.44813423 | G55: 10 | H55: -
B56: Greece | C56: Peristeri | D56: 2200000 | E56: 1380000 | F56: =E56/D56 -> 0.62727273 | G56: 6 | H56: Fiba Europe Cup - Top 8 / quarter-finals
B57: Greece | C57: Mykonos | D57: 2000000 | E57: 1380000 | F57: =E57/D57 -> 0.69 | G57: 7 | H57: -
B58: Poland | C58: Slask Wroclaw | D58: 2500000 | E58: 1400000 | F58: =+E58/D58 -> 0.56 | G58: 3 | H58: Eurocup - regular season 9 place
B59: Greece | C59: Iraklis | D59: 2200000 | E59: 1400000 | F59: =E59/D59 -> 0.63636364 | G59: 9 | H59: ENBL - Top 8 / quarter-finals
B60: Australia | C60: Brisbane Bullets | D60: 3000000 | E60: 1410000 | F60: =+E60/D60 -> 0.47 | G60: 10 | H60: -
B61: Hungary | C61: Atomeromu Paks | D61: 2254593 | E61: 1450000 | F61: =+E61/D61 -> 0.6431316 | G61: 4 | H61: -
B62: Israel | C62: Ironi Kiryat Ata | D62: 2366569.6 | E62: 1450000 | F62: =+E62/D62 -> 0.61270119 | G62: 10 | H62: -
B63: Israel | C63: Galil Elyon | D63: 2366569.6 | E63: 1450000 | F63: =+E63/D63 -> 0.61270119 | G63: 12 | H63: -
B64: Israel | C64: Maccabi Raanana | D64: 2366569.6 | E64: 1450000 | F64: =+E64/D64 -> 0.61270119 | G64: 14 | H64: -
B65: Poland | C65: Arka Gdynia | D65: 2354052 | E65: 1450000 | F65: =+E65/D65 -> 0.61595921 | G65: 6 | H65: -
B66: Germany | C66: Bamberg Baskets | D66: 5580000 | E66: 1460000 | F66: =+E66/D66 -> 0.26164875 | G66: 3 | H66: -
B67: Germany | C67: Syntainics MBC | D67: 4610000 | E67: 1470000 | F67: =+E67/D67 -> 0.31887202 | G67: 13 | H67: ENBL - F4 / third place
B68: Denmark | C68: Bakken Bears | D68: 2000000 | E68: 1480000 | F68: =+E68/D68 -> 0.74 | G68: 1 | H68: Fiba Europe Cup - did not advance from the group to the next round
B69: Austria | C69: Vienna Basket | D69: 2200000 | E69: 1500000 | F69: =+E69/D69 -> 0.68181818 | G69: 16 | H69: -
B70: Bosnia and Herzegovina | C70: KK Bosna | D70: 2100000 | E70: 1500000 | F70: =+E70/D70 -> 0.71428571 | G70: 7 | H70: Fiba Europe Cup - Top 8 / quarter-finals
B71: Hungary | C71: Szolnoki Olaj | D71: 2308343.7 | E71: 1500000 | F71: =+E71/D71 -> 0.64981657 | G71: 1 | H71: BCL - Play-in round
... B73: Turkey | C73: Buyukcekmece | D73: 2200000 | E73: 1500000 | F73: =+E73/D73 -> 0.68181818 | G73: 16 | H73: -
B74: Greece | C74: Kolossos Rhodes | D74: 2200000 | E74: 1500000 | F74: =E74/D74 -> 0.68181818 | G74: 8 | H74: -
B75: Australia | C75: New Zealand Breakers | D75: 3300000 | E75: 1550000 | F75: =+E75/D75 -> 0.46969697 | G75: 7 | H75: -
B76: Germany | C76: Gladiators Trier | D76: 4620000 | E76: 1560000 | F76: =+E76/D76 -> 0.33766234 | G76: 8 | H76: -
B77: Germany | C77: Science City Jena | D77: 4260000 | E77: 1570000 | F77: =+E77/D77 -> 0.3685446 | G77: 16 | H77: -
B78: France | C78: Nanterre | D78: 5627000 | E78: 1598000 | F78: =+E78/D78 -> 0.28398792 | G78: 3 | H78: -
B79: Hungary | C79: Falco Szombatey | D79: 2506275.7 | E79: 1600000 | F79: =+E79/D79 -> 0.63839745 | G79: 2 | H79: Fiba Europe Cup - F4 / semifinals
B80: Israel | C80: Hapoel Beer Sheeva | D80: 2662390.8 | E80: 1600000 | F80: =+E80/D80 -> 0.60096362 | G80: 8 | H80: -
B81: Israel | C81: Elitzur Maccabi Netanya | D81: 2662390.8 | E81: 1600000 | F81: =+E81/D81 -> 0.60096362 | G81: 13 | H81: -
B82: Portugal | C82: Porto | D82: 3100000 | E82: 1600000 | F82: =+E82/D82 -> 0.51612903 | G82: 3 | H82: Fiba Europe Cup - did not advance from the group to the next round
B83: Greece | C83: Promitheas Patras | D83: 2500000 | E83: 1600000 | F83: =E83/D83 -> 0.64 | G83: 10 | H83: BCL - Play-in round
B84: Australia | C84: Illawarra Hawks | D84: 3400000 | E84: 1620000 | F84: =+E84/D84 -> 0.47647059 | G84: 8 | H84: -
B85: France | C85: Cholet | D85: 6460000 | E85: 1631000 | F85: =+E85/D85 -> 0.25247678 | G85: 5 | H85: BCL - Play-in round
B86: France | C86: Saint-Quentin | D86: 4138000 | E86: 1663000 | F86: =+E86/D86 -> 0.40188497 | G86: 15 | H86: -
B87: Italy | C87: Cremona | D87: 4140000 | E87: 1700000 | F87: =+E87/D87 -> 0.41062802 | G87: 11 | H87: -
B88: Croatia | C88: Split | D88: 2737831 | E88: 1700000 | F88: =+E88/D88 -> 0.62092949 | G88: 18 | H88: -
B89: Israel | C89: Maccabi Ironi Ramat Gan | D89: 2810301.4 | E89: 1700000 | F89: =+E89/D89 -> 0.60491732 | G89: 9 | H89: -
B90: Turkey | C90: Merkezefendi | D90: 2500000 | E90: 1700000 | F90: =+E90/D90 -> 0.68 | G90: 9 | H90: -
B91: Belgium | C91: Antwerp Giants | D91: 2800000 | E91: 1719552 | F91: =+E91/D91 -> 0.61412571 | G91: 1 | H91: Fiba Europe Cup - did not advance from the group to the next round
B92: France | C92: Nancy | D92: 5836000 | E92: 1733000 | F92: =+E92/D92 -> 0.29694997 | G92: 10 | H92: -
B93: France | C93: Gravelines | D93: 5858000 | E93: 1778000 | F93: =+E93/D93 -> 0.30351656 | G93: 14 | H93: -
B94: Japan | C94: Shiga | D94: 8200000 | E94: 1800000 | F94: =+E94/D94 -> 0.2195122 | G94: 24 | H94: -
B95: Poland | C95: Anwil Wloclawek | D95: 3300000 | E95: 1800000 | F95: =+E95/D95 -> 0.54545455 | G95: 7 | H95: Fiba Europe Cup - did not advance from the group to the next round
... B119: France | C119: Bourg-en-Bresse | D119: 8122000 | E119: 2300000 | F119: =+E119/D119 -> 0.28318148 | G119: 7 | H119: Eurocup - Winners
B120: Greece | C120: Maroussi | D120: 3200000 | E120: 2300000 | F120: =E120/D120 -> 0.71875 | G120: 12 | H120: -
B121: Australia | C121: Sydney Kings | D121: 4700000 | E121: 2310000 | F121: =+E121/D121 -> 0.49148936 | G121: 1 | H121: -
B122: Italy | C122: Cantu | D122: 4676000 | E122: 2350000 | F122: =+E122/D122 -> 0.5025663 | G122: 14 | H122: -
B123: Spain | C123: Bibao Basket | D123: 5400000 | E123: 2392576 | F123: =+E123/D123 -> 0.44306963 | G123: 7 | H123: Fiba Europe Cup - Winner
B124: Belgium | C124: Filou Ostende | D124: 4000000 | E124: 2400000 | F124: =+E124/D124 -> 0.6 | G124: 2 | H124: BCL - did not advance from the group to the next round
B125: Japan | C125: Saga | D125: 9300000 | E125: 2400000 | F125: =+E125/D125 -> 0.25806452 | G125: 18 | H125: -
B126: Spain | C126: Basquet Girona | D126: 4200000 | E126: 2400000 | F126: =+E126/D126 -> 0.57142857 | G126: 12 | H126: -
B127: Australia | C127: Adelaide 36ers | D127: 5000000 | E127: 2460000 | F127: =+E127/D127 -> 0.492 | G127: 2 | H127: -
B128: Germany | C128: Rasta Vechta | D128: 5680000 | E128: 2460000 | F128: =+E128/D128 -> 0.43309859 | G128: 7 | H128: Fiba Europe Cup - did not advance from the group to the next round
B129: Israel | C129: Nes Ziona | D129: 4141496.8 | E129: 2500000 | F129: =+E129/D129 -> 0.60364649 | G129: 11 | H129: -
B130: Spain | C130: Basket Zaragoza | D130: 3900000 | E130: 2500000 | F130: =+E130/D130 -> 0.64102564 | G130: 15 | H130: Fiba Europe Cup - Top 16
B131: Turkey | C131: Karsiyaka | D131: 3500000 | E131: 2500000 | F131: =+E131/D131 -> 0.71428571 | G131: 14 | H131: -
B132: Germany | C132: MHP Riesen Ludwigsburg | D132: 5740000 | E132: 2520000 | F132: =+E132/D132 -> 0.43902439 | G132: 10 | H132: -
... B138: Italy | C138: Trento | D138: 6350000 | E138: 2650000 | F138: =+E138/D138 -> 0.41732283 | G138: 8 | H138: Eurocup -quarter-finals (Top 8)
B139: Greece | C139: Panionios | D139: 4000000 | E139: 2700000 | F139: =E139/D139 -> 0.675 | G139: 13 | H139: Eurocup - regular season 10 place
B140: Germany | C140: Wurzburg | D140: 6730000 | E140: 2750000 | F140: =+E140/D140 -> 0.40861813 | G140: 5 | H140: BCL - Top 16
B141: Germany | C141: Niners Chemnitz | D141: 7510000 | E141: 2760000 | F141: =+E141/D141 -> 0.36750999 | G141: 12 | H141: Eurocup - 1/8 finals
...

Sheet Attendance
B1: Season 25/26
B3: Prancūzijos lyga (Betclic Elite)
B4: Klubas | C4: Vidutinis žiūrovų skaičius | D4: Arena talpina | E4: Užpildymas | F4: Vieta nac. čemp. turnyrinėje lentelėje po reg. sezono
B5: Paris | C5: 6288 | D5: 6750 | E5: =C5/D5 -> 0.93155556 | F5: 1
B6: Strasbourg | C6: 5819 | D6: 6200 | E6: =C6/D6 -> 0.93854839 | F6: 8
B7: Nancy | C7: 5751 | D7: 5850 | E7: =C7/D7 -> 0.98307692 | F7: 10
B8: Asvel | C8: 5287 | D8: 5550 | E8: =C8/D8 -> 0.95261261 | F8: 4
B9: Le Mans | C9: 5228 | D9: 6000 | E9: =C9/D9 -> 0.87133333 | F9: 6
B10: Boulazac | C10: 4922 | D10: 5100 | E10: =C10/D10 -> 0.96509804 | F10: 12
B11: Cholet | C11: 4713 | D11: 4720 | E11: =C11/D11 -> 0.99851695 | F11: 5
B12: Chalon | C12: 4578 | D12: 4620 | E12: =C12/D12 -> 0.99090909 | F12: 9
B13: Limoges | C13: 4397 | D13: 4750 | E13: =C13/D13 -> 0.92568421 | F13: 13
B14: Nanterre | C14: 3614 | D14: 3950 | E14: =C14/D14 -> 0.91493671 | F14: 3
B15: Bourg-en-Bresse | C15: 3492 | D15: 3500 | E15: =C15/D15 -> 0.99771429 | F15: 7
B16: Dijon | C16: 3228 | D16: 3650 | E16: =C16/D16 -> 0.88438356 | F16: 11
... B20: Gravelines | C20: 2090 | D20: 2150 | E20: =C20/D20 -> 0.97209302 | F20: 14
B22: Vidurkis | C22: =average(C5:C20) -> 4236.75
B25: Vokietijos lyga (easyCredit BBL)
B26: Klubas | C26: Vidutinis žiūrovų skaičius | D26: Arena talpina | E26: Užpildymas | F26: Vieta nac. čemp. turnyrinėje lentelėje po reg. sezono | G26: https://easycredit-bbl.de/statistiken/zuschauer
B27: Alba Berlin | C27: 8616 | D27: 13488 / 8780 | E27: =C27/D27 -> #VALUE! | F27: 2
B28: Telekom Baskets Bonn | C28: 6471 | D28: 18500 / 6000 | E28: =C28/D28 -> #VALUE! | F28: 4
B29: FC Bayern | C29: 6452 | D29: 11500 / 6731 | E29: =C29/D29 -> #VALUE! | F29: 1
B30: EWE Baskets Oldenburg | C30: 6256 | D30: 6335 / 3148 | E30: =C30/D30 -> #VALUE! | F30: 11
B31: Ratiopharm Ulm | C31: 5584 | D31: 6000 | E31: =C31/D31 -> 0.93066667 | F31: 6
B32: Gladiators Trier | C32: 5351 | D32: 5400 | E32: =C32/D32 -> 0.99092593 | F32: 8
B33: Bamberg Baskets | C33: 5096 | D33: 5700 | E33: =C33/D33 -> 0.89403509 | F33: 3
B34: MLP Academics Heidelberg | C34: 4610 | D34: 14713 / 4521 | E34: =C34/D34 -> #VALUE! | F34: 18
B35: Niners Chemnitz | C35: 4602 | D35: 5000 | E35: =C35/D35 -> 0.9204 | F35: 12
B36: Frankfurt Skyliners | C36: 4321 | D36: 5002 | E36: =C36/D36 -> 0.86385446 | F36: 15
B37: Lowen Braunschweig | C37: 4212 | D37: 6358 | E37: =C37/D37 -> 0.66247248 | F37: 17
B38: Rostock Seawolves | C38: 4112 | D38: 5000 | E38: =C38/D38 -> 0.8224 | F38: 9
B39: MHP Riesen Ludwigsburg | C39: 3908 | D39: 4000 | E39: =C39/D39 -> 0.977 | F39: 10
B40: Hamburg Towers | C40: 3844 | D40: 12015 / 3400 | E40: =C40/D40 -> #VALUE! | F40: 14
B41: Rasta Vechta | C41: 3129 | D41: 3140 | E41: =C41/D41 -> 0.99649682 | F41: 7
B42: Wurzburg | C42: 3106 | D42: 3140 | E42: =C42/D42 -> 0.98917197 | F42: 5
B43: Science City Jena | C43: 2900 | D43: 3125 | E43: =C43/D43 -> 0.928 | F43: 16
B44: Syntainics MBC | C44: 2788 | D44: 12000 / 3000 | E44: =C44/D44 -> #VALUE! | F44: 13
B46: Vidurkis | C46: =average(C27:C44) -> 4742.1111
B49: Ispanijos lyga (liga Endesa)
B50: Klubas | C50: Vidutinis žiūrovų skaičius | D50: Arena talpina | E50: Užpildymas | F50: Vieta nac. čemp. turnyrinėje lentelėje po reg. sezono
B51: Valencia | C51: 11916 | D51: 15600 | E51: =C51/D51 -> 0.76384615 | F51: 2
B52: Unicaja | C52: 9206 | D52: 10699 | E52: =C52/D52 -> 0.86045425 | F52: 9
B53: San Pablo Burgos | C53: 9008 | D53: 9604 | E53: =C53/D53 -> 0.93794252 | F53: 13
B54: Baskonia | C54: 8685 | D54: 15504 | E54: =C54/D54 -> 0.56017802 | F54: 3
B55: Bibao Basket | C55: 8360 | D55: 10014 | E55: =C55/D55 -> 0.83483124 | F55: 7
B56: Real Madrid | C56: 7606 | D56: 13109 | E56: =C56/D56 -> 0.58021207 | F56: 1
B57: Basket Zaragoza | C57: 6906 | D57: 10744 | E57: =C57/D57 -> 0.64277736 | F57: 15
B58: UCAM Murcia | C58: 6890 | D58: 7454 | E58: =C58/D58 -> 0.92433593 | F58: 4
B59: Joventut Badalona | C59: 6859 | D59: 12760 | E59: =C59/D59 -> 0.53753918 | F59: 6
B60: Granada | C60: 6692 | D60: 8100 | E60: =C60/D60 -> 0.82617284 | F60: 18
B61: CB Gran Canaria | C61: 6342 | D61: 9870 | E61: =C61/D61 -> 0.64255319 | F61: 17
B62: Lleida | C62: 5584 | D62: 6100 | E62: =C62/D62 -> 0.91540984 | F62: 14
... B68: Andorra | C68: 3471 | D68: 5001 | E68: =C68/D68 -> 0.69406119 | F68: 16
B70: Vidurkis | C70: =average(C51:C68) -> 6807.1111
B73: Italijos lyga (Lega A)
B74: Klubas | C74: Vidutinis žiūrovų skaičius | D74: Arena talpina | E74: Užpildymas | F74: Vieta nac. čemp. turnyrinėje lentelėje po reg. sezono | G74: Vidutinės rungtynių pajamos | H74: https://www.legabasket.it/news/138712/pubblico-regular-season-2025-26
B75: Trapani | C75: - | D75: - | E75: #VALUE! | F75: 16 | G75: -
B76: Olimpia Milano | C76: 6519 | D76: 10060 | E76: =C76/D76 -> 0.64801193 | F76: 3 | G76: 122 878 € | H76: Dvi arenos. 9 rungtynės talpinančioj 12700 ;5 rungt 5309 talpinančioje
B77: Virtus Bologna | C77: 6206 | D77: 8891 | E77: =C77/D77 -> 0.69800922 | F77: 1 | G77: 115 943 € | H77: Dvi arenos. 10 rungtynių talpinančioj 10220 ;4 rungt 5570 talpinančioje
B78: Trieste | C78: 5512 | D78: 6736 | E78: =C78/D78 -> 0.81828979 | F78: 7 | G78: 104 377 €
B79: Cantu | C79: 4757 | D79: 6272 | E79: =C79/D79 -> 0.75845026 | F79: 14 | G79: 57 140 €
B80: Brescia | C80: 4683 | D80: 5164 | E80: =C80/D80 -> 0.90685515 | F80: 2 | G80: 71 097 €
B81: Varese | C81: 4485 | D81: 5107 | E81: =C81/D81 -> 0.87820638 | F81: 9 | G81: 88 022 €
B82: Trento | C82: 3877 | D82: 4000 | E82: =C82/D82 -> 0.96925 | F82: 8 | G82: 36 607 €
B83: Treviso | C83: 3800 | D83: 5344 | E83: =C83/D83 -> 0.71107784 | F83: 12 | G83: 41 805 €
B84: Reggiana | C84: 3629 | D84: 4530 | E84: =C84/D84 -> 0.80110375 | F84: 6 | G84: 76 998 €
B85: Tortona | C85: 3600 | D85: 5000 | E85: =C85/D85 -> 0.72 | F85: 5 | G85: 70 572 €
B86: Udine | C86: 3462 | D86: 3500 | E86: =C86/D86 -> 0.98914286 | F86: 13 | G86: 40 609 €
B87: Venezia | C87: 3326 | D87: 3509 | E87: =C87/D87 -> 0.94784839 | F87: 4 | G87: 23 138 €
B88: Sassari | C88: 2927 | D88: 5000 | E88: =C88/D88 -> 0.5854 | F88: 15 | G88: 50 247 €
B89: Napoli | C89: 2596 | D89: 3890 | E89: =C89/D89 -> 0.66735219 | F89: 10 | G89: 34 334 €
B90: Cremona | C90: 2193 | D90: 3511 | E90: =C90/D90 -> 0.62460837 | F90: 11 | G90: 22 338 €
B92: Vidurkis | C92: =average(C76:C90) -> 4104.8
B96: Lietuvos lyga (LKL)
B97: Klubas | C97: Vidutinis žiūrovų skaičius | D97: Arena talpina | E97: Užpildymas | F97: Vieta nac. čemp. turnyrinėje lentelėje po reg. sezono
B98: Žalgiris | C98: 4342 | D98: 15415 | E98: =C98/D98 -> 0.28167369 | F98: 1
B99: Rytas | C99: 2832 | D99: 5463 | E99: =C99/D99 -> 0.51839649 | F99: 2
B100: Šiauliai | C100: 2489 | D100: 5500 | E100: =C100/D100 -> 0.45254545 | F100: 4
B101: Neptūnas | C101: 2325 | D101: 6200 | E101: =C101/D101 -> 0.375 | F101: 3
B102: Lietkabelis | C102: 1880 | D102: 5600 | E102: =C102/D102 -> 0.33571429 | F102: 5
B103: Juventus | C103: 1375 | D103: 2500 | E103: =C103/D103 -> 0.55 | F103: 7
B104: Nevėžis | C104: 1334 | D104: 2200 | E104: =C104/D104 -> 0.60636364 | F104: 9
B105: Gargždai | C105: 1294 | D105: 1500 | E105: =C105/D105 -> 0.86266667 | F105: 6
B106: Jonava | C106: 914 | D106: 2246 | E106: =C106/D106 -> 0.40694568 | F106: 8
B108: Vidurkis | C108: =average(C98:C106) -> 2087.2222

Sheet Player Salaries
C2: Dollar to euro conversion rate
C3: 2005 summer | D3: 1 usd 0.81 eur
C4: 2007 summer | D4: 1 usd 0.72 eur
C5: 2008 summer | D5: 1 usd 0.65 eur
C6: 2009 summer | D6: 1 usd 0.7 eur
C7: 2010 summer | D7: 1 usd 0.8 eur
C8: 2011 summer | D8: 1 usd 0.7 eur
C9: 2012 summer | D9: 1 usd 0.8 eur
C10: 2013 summer | D10: 1 usd 0.75 eur
C11: 2014 summer | D11: 1 usd 0.75 eur
C12: 2015 summer | D12: 1 usd 0.9 eur
C13: 2016 summer | D13: 1 usd 0.9 eur
C14: 2017 summer | D14: 1 usd 0.86 eur
... C23: 2026 summer | D23: 1 usd 0.88 eur
B25: Role | C25: Name | D25: Country | E25: Team | F25: Season | G25: Contract value | H25: Contract lenght | I25: Monthly Salary | J25: Source 1 | K25: Source 2 | L25: Source 3
B26: Player | C26: Jonas Mačiulis | D26: Greece | E26: AEK | F26: 19/20 | G26: 220000 | H26: Full season | I26: =G26/10 -> 22000 | J26: https://assets.fiba.basketball/image/upload/v1726052961/Corporate%20Images/HQ%20Departments/Legal/BAT%20Awards/1752-21.pdf
B27: Player | C27: Lior Eliyahu | D27: Israel | E27: Hapoel Jerusalem | F27: 18/19 | G27: 425000 | H27: Full season | I27: =G27/10 -> 42500 | J27: https://www.sport5.co.il/articles.aspx?FolderID=407&docID=293704
B28: Player | C28: Žygimantas Janavičius | D28: Lithuania | E28: Klaipėdos Neptūnas | F28: 20/21 | G28: 60000 | H28: Full season | I28: =G28/10 -> 6000 | J28: https://www.15min.lt/naujiena/prenumerata/ivykiai/top-30-geriausiai-apmokamu-lkl-zaideju-zalgirieciu-dominavimas-ir-svarbios-detales-1226-1370624
B29: Player | C29: Mindaugas Kupšas | D29: Lithuania | E29: Utenos Juventus | F29: 20/21 | G29: 65000 | H29: Full season | I29: =G29/10 -> 6500 | J29: https://www.15min.lt/naujiena/prenumerata/ivykiai/top-30-geriausiai-apmokamu-lkl-zaideju-zalgirieciu-dominavimas-ir-svarbios-detales-1226-1370624
B30: Player | C30: Julius Jucikas | D30: Lithuania | E30: Utenos Juventus | F30: 20/21 | G30: 65000 | H30: Full season | I30: =G30/10 -> 6500 | J30: https://www.15min.lt/naujiena/prenumerata/ivykiai/top-30-geriausiai-apmokamu-lkl-zaideju-zalgirieciu-dominavimas-ir-svarbios-detales-1226-1370624
B31: Player | C31: Paulius Valinskas | D31: Lithuania | E31: Lietkabelis | F31: 20/21 | G31: 65000 | H31: Full season | I31: =G31/10 -> 6500 | J31: https://www.15min.lt/naujiena/prenumerata/ivykiai/top-30-geriausiai-apmokamu-lkl-zaideju-zalgirieciu-dominavimas-ir-svarbios-detales-1226-1370624
B32: Player | C32: Rokas Jokubaitis | D32: Lithuania | E32: Kauno Žalgiris | F32: 20/21 | G32: 70000 | H32: Full season | I32: =G32/10 -> 7000 | J32: https://www.15min.lt/naujiena/prenumerata/ivykiai/top-30-geriausiai-apmokamu-lkl-zaideju-zalgirieciu-dominavimas-ir-svarbios-detales-1226-1370624
B33: Player | C33: Kyle Vinales | D33: Lithuania | E33: Lietkabelis | F33: 20/21 | G33: 70000 | H33: Full season | I33: =G33/10 -> 7000 | J33: https://www.15min.lt/naujiena/prenumerata/ivykiai/top-30-geriausiai-apmokamu-lkl-zaideju-zalgirieciu-dominavimas-ir-svarbios-detales-1226-1370624
B34: Player | C34: Glen Rice Jr. | D34: Lithuania | E34: Utenos Juventus | F34: 20/21 | G34: 70000 | H34: Full season | I34: =G34/10 -> 7000 | J34: https://www.15min.lt/naujiena/prenumerata/ivykiai/top-30-geriausiai-apmokamu-lkl-zaideju-zalgirieciu-dominavimas-ir-svarbios-detales-1226-1370624
B35: Player | C35: Mindaugas Lukauskis | D35: Lithuania | E35: Rytas Vilnius | F35: 14/15 | G35: 80000 | H35: Full season | I35: =G35/10 -> 8000 | J35: https://www.krepsinis.net/naujiena/10-lkl-zaidzianciu-lietuviu-kurie-uzdirba-daugiausiai/248876 | K35: https://www.basketnews.lt/news-83614-kiek-uzdirba-didziuju-lkl-klubu-krepsininkai.html
B36: Player | C36: Artūras Valeika | D36: Lithuania | E36: Rytas Vilnius | F36: 14/15 | G36: 60000 | H36: Full season | I36: =G36/10 -> 6000 | J36: https://www.basketnews.lt/news-83614-kiek-uzdirba-didziuju-lkl-klubu-krepsininkai.html
B37: Player | C37: Marin Marič | D37: Lithuania | E37: Lietkabelis | F37: 20/21 | G37: 70000 | H37: Full season | I37: =G37/10 -> 7000 | J37: https://www.15min.lt/naujiena/prenumerata/ivykiai/top-30-geriausiai-apmokamu-lkl-zaideju-zalgirieciu-dominavimas-ir-svarbios-detales-1226-1370624
B38: Player | C38: Žygimantas Janavičius | D38: Lithuania | E38: Rytas Vilnius | F38: 14/15 | G38: 80000 | H38: Full season | I38: =G38/10 -> 8000 | J38: https://www.basketnews.lt/news-83614-kiek-uzdirba-didziuju-lkl-klubu-krepsininkai.html
B39: Player | C39: Gytis Masiulis | D39: Lithuania | E39: Lietkabelis | F39: 20/21 | G39: 90000 | H39: Full season | I39: =G39/10 -> 9000 | J39: https://www.15min.lt/naujiena/prenumerata/ivykiai/top-30-geriausiai-apmokamu-lkl-zaideju-zalgirieciu-dominavimas-ir-svarbios-detales-1226-1370624
B40: Player | C40: Kostas Sloukas | D40: Greece | E40: Panathinaikos | F40: 24/25 | G40: 2680000 | H40: Full season | I40: =G40/10 -> 268000 | J40: https://www.basketnews.lt/news-215342-atskleistos-grigonio-ir-kitu-pao-zaideju-algos.html | K40: https://www.eurohoops.net/en/trademarks/1747585/panathinaikos-olympiacos-player-contracts-euroleague/
B41: Player | C41: Kendrick Nunn | D41: Greece | E41: Panathinaikos | F41: 24/25 | G41: 2390000 | H41: Full season | I41: =G41/10 -> 239000 | J41: https://www.basketnews.lt/news-215342-atskleistos-grigonio-ir-kitu-pao-zaideju-algos.html | K41: https://www.eurohoops.net/en/trademarks/1747585/panathinaikos-olympiacos-player-contracts-euroleague/
B42: Player | C42: Juancho Hernangomez | D42: Greece | E42: Panathinaikos | F42: 24/25 | G42: 2100000 | H42: Full season | I42: =G42/10 -> 210000 | J42: https://www.basketnews.lt/news-215342-atskleistos-grigonio-ir-kitu-pao-zaideju-algos.html | K42: https://www.eurohoops.net/en/trademarks/1747585/panathinaikos-olympiacos-player-contracts-euroleague/
B43: Player | C43: Lorenzo Brown | D43: Greece | E43: Panathinaikos | F43: 24/25 | G43: 1900000 | H43: Full season | I43: =G43/10 -> 190000 | J43: https://www.basketnews.lt/news-215342-atskleistos-grigonio-ir-kitu-pao-zaideju-algos.html | K43: https://www.eurohoops.net/en/trademarks/1747585/panathinaikos-olympiacos-player-contracts-euroleague/ | L43: https://x.com/hizlihucum/status/1803455514354876516
B44: Player | C44: Mathias Lessort | D44: Greece | E44: Panathinaikos | F44: 24/25 | G44: 1700000 | H44: Full season | I44: =G44/10 -> 170000 | J44: https://www.basketnews.lt/news-215342-atskleistos-grigonio-ir-kitu-pao-zaideju-algos.html | K44: https://www.eurohoops.net/en/trademarks/1747585/panathinaikos-olympiacos-player-contracts-euroleague/
B45: Player | C45: Cedi Osman | D45: Greece | E45: Panathinaikos | F45: 24/25 | G45: 1600000 | H45: 9 months | I45: =G45/9 -> 177777.78 | J45: https://www.basketnews.lt/news-215342-atskleistos-grigonio-ir-kitu-pao-zaideju-algos.html | K45: https://www.eurohoops.net/en/trademarks/1747585/panathinaikos-olympiacos-player-contracts-euroleague/
B46: Player | C46: Marius Grigonis | D46: Greece | E46: Panathinaikos | F46: 24/25 | G46: 1100000 | H46: Full season | I46: =G46/10 -> 110000 | J46: https://www.basketnews.lt/news-215342-atskleistos-grigonio-ir-kitu-pao-zaideju-algos.html | K46: https://www.eurohoops.net/en/trademarks/1747585/panathinaikos-olympiacos-player-contracts-euroleague/
B47: Player | C47: Omer Yurtseven | D47: Greece | E47: Panathinaikos | F47: 24/25 | G47: 1000000 | H47: Full season | I47: =G47/10 -> 100000 | J47: https://www.basketnews.lt/news-215342-atskleistos-grigonio-ir-kitu-pao-zaideju-algos.html | K47: https://www.eurohoops.net/en/trademarks/1747585/panathinaikos-olympiacos-player-contracts-euroleague/
B48: Player | C48: Jerian Grant | D48: Greece | E48: Panathinaikos | F48: 24/25 | G48: 1000000 | H48: Full season | I48: =G48/10 -> 100000 | J48: https://www.basketnews.lt/news-215342-atskleistos-grigonio-ir-kitu-pao-zaideju-algos.html | K48: https://www.eurohoops.net/en/trademarks/1747585/panathinaikos-olympiacos-player-contracts-euroleague/
B49: Player | C49: Ioannis Papapetrou | D49: Greece | E49: Panathinaikos | F49: 24/25 | G49: 800000 | H49: Full season | I49: =G49/10 -> 80000 | J49: https://www.basketnews.lt/news-215342-atskleistos-grigonio-ir-kitu-pao-zaideju-algos.html | K49: https://www.eurohoops.net/en/trademarks/1747585/panathinaikos-olympiacos-player-contracts-euroleague/
B50: Player | C50: Konstantinos Mitoglou | D50: Greece | E50: Panathinaikos | F50: 24/25 | G50: 800000 | H50: Full season | I50: =G50/10 -> 80000 | J50: https://www.basketnews.lt/news-215342-atskleistos-grigonio-ir-kitu-pao-zaideju-algos.html | K50: https://www.eurohoops.net/en/trademarks/1747585/panathinaikos-olympiacos-player-contracts-euroleague/
B51: Player | C51: Kostas Antetokounmpo | D51: Greece | E51: Panathinaikos | F51: 24/25 | G51: 500000 | H51: Full season | I51: =G51/10 -> 50000 | J51: https://www.basketnews.lt/news-215342-atskleistos-grigonio-ir-kitu-pao-zaideju-algos.html | K51: https://www.eurohoops.net/en/trademarks/1747585/panathinaikos-olympiacos-player-contracts-euroleague/
B52: Player | C52: Panagiotis Kalaitzakis | D52: Greece | E52: Panathinaikos | F52: 24/25 | G52: 350000 | H52: Full season | I52: =G52/10 -> 35000 | J52: https://www.basketnews.lt/news-215342-atskleistos-grigonio-ir-kitu-pao-zaideju-algos.html | K52: https://www.eurohoops.net/en/trademarks/1747585/panathinaikos-olympiacos-player-contracts-euroleague/
B53: Player | C53: Dimitris Moraitis | D53: Greece | E53: Panathinaikos | F53: 24/25 | G53: 250000 | H53: Full season | I53: =G53/10 -> 25000 | J53: https://www.basketnews.lt/news-215342-atskleistos-grigonio-ir-kitu-pao-zaideju-algos.html | K53: https://www.eurohoops.net/el/trademarks-el/1747652/panathinaikos-olimpiakos-afta-ine-ta-simvolea-ton-dio-megaliteron-budget-stin-evroligka/
B54: Player | C54: Wenyen Gabriel | D54: Greece | E54: Panathinaikos | F54: 24/25 | G54: 500000 | H54: 6 months | I54: =G54/6 -> 83333.333 | J54: https://www.eurohoops.net/el/trademarks-el/1747652/panathinaikos-olimpiakos-afta-ine-ta-simvolea-ton-dio-megaliteron-budget-stin-evroligka/ | K54: https://www.eurohoops.net/en/trademarks/1747585/panathinaikos-olympiacos-player-contracts-euroleague/
B55: Player | C55: Alexandros Samodurov | D55: Greece | E55: Panathinaikos | F55: 24/25 | G55: 200000 | H55: Full season | I55: =G55/10 -> 20000 | J55: https://www.basketnews.lt/news-215342-atskleistos-grigonio-ir-kitu-pao-zaideju-algos.html | K55: https://www.eurohoops.net/en/trademarks/1747585/panathinaikos-olympiacos-player-contracts-euroleague/
B56: Coach | C56: Ergin Ataman | D56: Greece | E56: Panathinaikos | F56: 24/25 | G56: 1300000 | H56: Full season | I56: =G56/10 -> 130000 | J56: https://www.basketnews.lt/news-215342-atskleistos-grigonio-ir-kitu-pao-zaideju-algos.html | K56: https://www.eurohoops.net/en/trademarks/1747585/panathinaikos-olympiacos-player-contracts-euroleague/
B57: Coach | C57: Ergin Ataman | D57: Greece | E57: Panathinaikos | F57: 23/24 | G57: =1200000*0.9 -> 1080000 | H57: Full season | I57: =G57/10 -> 108000 | J57: https://www.pianetabasket.com/euroleague/mercato-el-panathinaikos-un-nuovo-lungo-accordo-per-ergin-ataman-305865
B58: Player | C58: Kendrick Nunn | D58: Greece | E58: Panathinaikos | F58: 25/26 | G58: 4500000 | H58: Full season | I58: =G58/10 -> 450000 | J58: https://www.sport24.gr/basket/euroleague-basketball/panathinaikos-aktor-i-axia-ton-prasinon-simvolaion-apogeiothike-kai-angizei-ta-25-ekatommiria/ | K58: https://basketnews.com/news-222625-dimitris-giannakopoulos-announced-extensions-for-nunn-and-osman.html
B59: Player | C59: Kostas Sloukas | D59: Greece | E59: Panathinaikos | F59: 25/26 | G59: 2800000 | H59: Full season | I59: =G59/10 -> 280000 | J59: https://www.sport24.gr/basket/euroleague-basketball/panathinaikos-aktor-i-axia-ton-prasinon-simvolaion-apogeiothike-kai-angizei-ta-25-ekatommiria/
B60: Player | C60: Mathias Lessort | D60: Greece | E60: Panathinaikos | F60: 25/26 | G60: 2500000 | H60: Full season | I60: =G60/10 -> 250000 | J60: https://www.sport24.gr/basket/euroleague-basketball/panathinaikos-aktor-i-axia-ton-prasinon-simvolaion-apogeiothike-kai-angizei-ta-25-ekatommiria/ | K60: https://x.com/Andrea__Calzoni/status/1873296957445459991
B61: Player | C61: Richaun Holmes | D61: Greece | E61: Panathinaikos | F61: 25/26 | G61: 2350000 | H61: Full season | I61: =G61/10 -> 235000 | J61: https://www.sport24.gr/basket/euroleague-basketball/panathinaikos-aktor-i-axia-ton-prasinon-simvolaion-apogeiothike-kai-angizei-ta-25-ekatommiria/
B62: Player | C62: Juancho Hernangomez | D62: Greece | E62: Panathinaikos | F62: 25/26 | G62: 2200000 | H62: Full season | I62: =G62/10 -> 220000 | J62: https://www.sport24.gr/basket/euroleague-basketball/panathinaikos-aktor-i-axia-ton-prasinon-simvolaion-apogeiothike-kai-angizei-ta-25-ekatommiria/ | K62: https://x.com/Andrea__Calzoni/status/1875621273579245870
B63: Player | C63: T.J. Shorts | D63: Greece | E63: Panathinaikos | F63: 25/26 | G63: 2100000 | H63: Full season | I63: =G63/10 -> 210000 | J63: https://www.sport24.gr/basket/euroleague-basketball/panathinaikos-aktor-i-axia-ton-prasinon-simvolaion-apogeiothike-kai-angizei-ta-25-ekatommiria/
B64: Player | C64: Cedi Osman | D64: Greece | E64: Panathinaikos | F64: 25/26 | G64: 1500000 | H64: Full season | I64: =G64/10 -> 150000 | J64: https://www.sport24.gr/basket/euroleague-basketball/panathinaikos-aktor-i-axia-ton-prasinon-simvolaion-apogeiothike-kai-angizei-ta-25-ekatommiria/
B65: Player | C65: Jerian Grant | D65: Greece | E65: Panathinaikos | F65: 25/26 | G65: 1200000 | H65: Full season | I65: =G65/10 -> 120000 | J65: https://www.sport24.gr/basket/euroleague-basketball/panathinaikos-aktor-i-axia-ton-prasinon-simvolaion-apogeiothike-kai-angizei-ta-25-ekatommiria/
B66: Player | C66: Marius Grigonis | D66: Greece | E66: Panathinaikos | F66: 25/26 | G66: 1200000 | H66: Full season | I66: =G66/10 -> 120000 | J66: https://www.sport24.gr/basket/euroleague-basketball/panathinaikos-aktor-i-axia-ton-prasinon-simvolaion-apogeiothike-kai-angizei-ta-25-ekatommiria/
B67: Player | C67: Omer Yurtseven | D67: Greece | E67: Panathinaikos | F67: 25/26 | G67: 1200000 | H67: Full season | I67: =G67/10 -> 120000 | J67: https://www.sport24.gr/basket/euroleague-basketball/panathinaikos-aktor-i-axia-ton-prasinon-simvolaion-apogeiothike-kai-angizei-ta-25-ekatommiria/
B68: Player | C68: Nikos Rogkavopoulos | D68: Greece | E68: Panathinaikos | F68: 25/26 | G68: 1300000 | H68: Full season | I68: =G68/10 -> 130000 | J68: https://www.sport24.gr/basket/euroleague-basketball/panathinaikos-aktor-i-axia-ton-prasinon-simvolaion-apogeiothike-kai-angizei-ta-25-ekatommiria/ | K68: https://x.com/Andrea__Calzoni/status/1933796278523052364
B69: Player | C69: Konstantinos Mitoglou | D69: Greece | E69: Panathinaikos | F69: 25/26 | G69: 750000 | H69: Full season | I69: =G69/10 -> 75000 | J69: https://www.sport24.gr/basket/euroleague-basketball/panathinaikos-aktor-i-axia-ton-prasinon-simvolaion-apogeiothike-kai-angizei-ta-25-ekatommiria/
B70: Player | C70: Vassilis Toliopoulos | D70: Greece | E70: Panathinaikos | F70: 25/26 | G70: 500000 | H70: Full season | I70: =G70/10 -> 50000 | J70: https://www.sport24.gr/basket/euroleague-basketball/panathinaikos-aktor-i-axia-ton-prasinon-simvolaion-apogeiothike-kai-angizei-ta-25-ekatommiria/
B71: Player | C71: Panagiotis Kalaitzakis | D71: Greece | E71: Panathinaikos | F71: 25/26 | G71: 350000 | H71: Full season | I71: =G71/10 -> 35000 | J71: https://www.sport24.gr/basket/euroleague-basketball/panathinaikos-aktor-i-axia-ton-prasinon-simvolaion-apogeiothike-kai-angizei-ta-25-ekatommiria/
B72: Player | C72: Alexandros Samodurov | D72: Greece | E72: Panathinaikos | F72: 25/26 | G72: 200000 | H72: Full season | I72: =G72/10 -> 20000 | J72: https://www.sport24.gr/basket/euroleague-basketball/panathinaikos-aktor-i-axia-ton-prasinon-simvolaion-apogeiothike-kai-angizei-ta-25-ekatommiria/
B73: Player | C73: Kenneth Faried | D73: Greece | E73: Panathinaikos | F73: 25/26 | G73: 200000 | H73: 2 months | I73: =G73/2 -> 100000 | J73: https://www.sport24.gr/basket/euroleague-basketball/panathinaikos-aktor-i-axia-ton-prasinon-simvolaion-apogeiothike-kai-angizei-ta-25-ekatommiria/
B74: Player | C74: Nigel Hayes - Davis | D74: Greece | E74: Panathinaikos | F74: 25/26 | G74: 2000000 | H74: 4 months | I74: =G74/4 -> 500000 | J74: https://www.protothema.gr/sports/article/1772720/panathinaikos-to-muthiko-sumvolaio-pou-tha-parei-heiz-devis-stin-ellada-den-xepernaei-to-kase-tou-nan/
B75: Player | C75: Sasha Vezenkov | D75: Greece | E75: Olympiacos | F75: 25/26 | G75: 3700000 | H75: Full season | I75: =G75/10 -> 370000 | J75: https://www.sport24.gr/basket/euroleague-basketball/olimpiakos-i-pio-akrivi-omada-olon-ton-epoxon-afta-einai-ta-xrisa-simvolaia-ton-erithrolefkon/
B76: Player | C76: Evan Fournier | D76: Greece | E76: Olympiacos | F76: 25/26 | G76: 3000000 | H76: Full season | I76: =G76/10 -> 300000 | J76: https://www.sport24.gr/basket/euroleague-basketball/olimpiakos-i-pio-akrivi-omada-olon-ton-epoxon-afta-einai-ta-xrisa-simvolaia-ton-erithrolefkon/ | K76: 9M/ 3 Y
B77: Player | C77: Nikola Milutinov | D77: Greece | E77: Olympiacos | F77: 25/26 | G77: 2300000 | H77: Full season | I77: =G77/10 -> 230000 | J77: https://www.sport24.gr/basket/euroleague-basketball/olimpiakos-i-pio-akrivi-omada-olon-ton-epoxon-afta-einai-ta-xrisa-simvolaia-ton-erithrolefkon/ | K77: https://x.com/Andrea__Calzoni/status/1932710543149724138
B78: Player | C78: Moustapha Fall | D78: Greece | E78: Olympiacos | F78: 25/26 | G78: 1900000 | H78: Full season | I78: =G78/10 -> 190000 | J78: https://www.sport24.gr/basket/euroleague-basketball/olimpiakos-i-pio-akrivi-omada-olon-ton-epoxon-afta-einai-ta-xrisa-simvolaia-ton-erithrolefkon/
B79: Player | C79: Tyler Dorsey | D79: Greece | E79: Olympiacos | F79: 25/26 | G79: 1400000 | H79: Full season | I79: =G79/10 -> 140000 | J79: https://www.sport24.gr/basket/euroleague-basketball/olimpiakos-i-pio-akrivi-omada-olon-ton-epoxon-afta-einai-ta-xrisa-simvolaia-ton-erithrolefkon/
B80: Player | C80: Kostas Papanikolaou | D80: Greece | E80: Olympiacos | F80: 25/26 | G80: 1200000 | H80: Full season | I80: =G80/10 -> 120000 | J80: https://www.sport24.gr/basket/euroleague-basketball/olimpiakos-i-pio-akrivi-omada-olon-ton-epoxon-afta-einai-ta-xrisa-simvolaia-ton-erithrolefkon/
B81: Player | C81: Alec Peters | D81: Greece | E81: Olympiacos | F81: 25/26 | G81: 1100000 | H81: Full season | I81: =G81/10 -> 110000 | J81: https://www.sport24.gr/basket/euroleague-basketball/olimpiakos-i-pio-akrivi-omada-olon-ton-epoxon-afta-einai-ta-xrisa-simvolaia-ton-erithrolefkon/
B82: Player | C82: Donta Hall | D82: Greece | E82: Olympiacos | F82: 25/26 | G82: 1000000 | H82: Full season | I82: =G82/10 -> 100000 | J82: https://www.sport24.gr/basket/euroleague-basketball/olimpiakos-i-pio-akrivi-omada-olon-ton-epoxon-afta-einai-ta-xrisa-simvolaia-ton-erithrolefkon/ | K82: https://x.com/hizlihucum/status/1946533554898264078
B83: Player | C83: Tyson Ward | D83: Greece | E83: Olympiacos | F83: 25/26 | G83: 900000 | H83: Full season | I83: =G83/10 -> 90000 | J83: https://www.sport24.gr/basket/euroleague-basketball/olimpiakos-i-pio-akrivi-omada-olon-ton-epoxon-afta-einai-ta-xrisa-simvolaia-ton-erithrolefkon/ | K83: https://x.com/hizlihucum/status/1928812864757747719
B84: Player | C84: Thomas Walkup | D84: Greece | E84: Olympiacos | F84: 25/26 | G84: 900000 | H84: Full season | I84: =G84/10 -> 90000 | J84: https://www.sport24.gr/basket/euroleague-basketball/olimpiakos-i-pio-akrivi-omada-olon-ton-epoxon-afta-einai-ta-xrisa-simvolaia-ton-erithrolefkon/
B85: Player | C85: Frank Ntilikina | D85: Greece | E85: Olympiacos | F85: 25/26 | G85: 900000 | H85: Full season | I85: =G85/10 -> 90000 | J85: https://www.sport24.gr/basket/euroleague-basketball/olimpiakos-i-pio-akrivi-omada-olon-ton-epoxon-afta-einai-ta-xrisa-simvolaia-ton-erithrolefkon/
B86: Player | C86: Keenan Evans | D86: Greece | E86: Olympiacos | F86: 25/26 | G86: 900000 | H86: Full season | I86: =G86/10 -> 90000 | J86: https://www.sport24.gr/basket/euroleague-basketball/olimpiakos-i-pio-akrivi-omada-olon-ton-epoxon-afta-einai-ta-xrisa-simvolaia-ton-erithrolefkon/
B87: Player | C87: Monte Morris | D87: Greece | E87: Olympiacos | F87: 25/26 | G87: 800000 | H87: 7 months | I87: =G87/7 -> 114285.71 | J87: https://www.sport24.gr/basket/euroleague-basketball/olimpiakos-i-pio-akrivi-omada-olon-ton-epoxon-afta-einai-ta-xrisa-simvolaia-ton-erithrolefkon/
B88: Player | C88: Tyrique Jones | D88: Greece | E88: Olympiacos | F88: 25/26 | G88: 750000 | H88: 6 months | I88: =G88/6 -> 125000 | J88: https://www.sport24.gr/basket/euroleague-basketball/olimpiakos-i-pio-akrivi-omada-olon-ton-epoxon-afta-einai-ta-xrisa-simvolaia-ton-erithrolefkon/ | K88: https://x.com/Andrea__Calzoni/status/2008140924724142477
B89: Player | C89: Shaquielle McKissic | D89: Greece | E89: Olympiacos | F89: 25/26 | G89: 700000 | H89: Full season | I89: =G89/10 -> 70000 | J89: https://www.sport24.gr/basket/euroleague-basketball/olimpiakos-i-pio-akrivi-omada-olon-ton-epoxon-afta-einai-ta-xrisa-simvolaia-ton-erithrolefkon/
B90: Player | C90: Cory Joseph | D90: Greece | E90: Olympiacos | F90: 25/26 | G90: 500000 | H90: 5 months | I90: =G90/5 -> 100000 | J90: https://www.sport24.gr/basket/euroleague-basketball/olimpiakos-i-pio-akrivi-omada-olon-ton-epoxon-afta-einai-ta-xrisa-simvolaia-ton-erithrolefkon/
B91: Player | C91: Giannoulis Larentzakis | D91: Greece | E91: Olympiacos | F91: 25/26 | G91: 500000 | H91: Full season | I91: =G91/10 -> 50000 | J91: https://www.sport24.gr/basket/euroleague-basketball/olimpiakos-i-pio-akrivi-omada-olon-ton-epoxon-afta-einai-ta-xrisa-simvolaia-ton-erithrolefkon/ | K91: https://www.athletiko.gr/ayto-einai-to-deal-olympiakoy-larentzaki-mechri-to-2028-23318 | L91: 1.5 / 3 y
B92: Player | C92: Omiros Netzipoglou | D92: Greece | E92: Olympiacos | F92: 25/26 | G92: 225000 | H92: Full season | I92: =G92/10 -> 22500 | J92: https://www.sport24.gr/basket/euroleague-basketball/olimpiakos-i-pio-akrivi-omada-olon-ton-epoxon-afta-einai-ta-xrisa-simvolaia-ton-erithrolefkon/ | K92: https://www.sport24.gr/basket/aek-metagrafes-telos-o-netzipoglou-apo-tin-enosi-anakoinonetai-apo-ton-olimpiako/
B93: Player | C93: Dovydas Giedraitis | D93: Lithuania | E93: Lietkabelis | F93: 21/22 | G93: 60000 | H93: Full season | I93: =G93/10 -> 6000 | J93: https://www.15min.lt/24sek/naujiena/lietuva/zalgirieciu-dominavimas-daugiausiai-uzdirbanciu-lkl-zaideju-top-40-875-1641660
B94: Player | C94: Martynas Gecevičius | D94: Lithuania | E94: Utenos Juventus | F94: 21/22 | G94: 60000 | H94: Full season | I94: =G94/10 -> 6000 | J94: https://www.15min.lt/24sek/naujiena/lietuva/zalgirieciu-dominavimas-daugiausiai-uzdirbanciu-lkl-zaideju-top-40-875-1641660
B95: Player | C95: Randy Culpepper | D95: Lithuania | E95: Pasvalio Pieno Žvaigždės | F95: 21/22 | G95: 60000 | H95: Full season | I95: =G95/10 -> 6000 | J95: https://www.15min.lt/24sek/naujiena/lietuva/zalgirieciu-dominavimas-daugiausiai-uzdirbanciu-lkl-zaideju-top-40-875-1641660
B96: Player | C96: Jonathan Elmore | D96: Lithuania | E96: Šiauliai | F96: 21/22 | G96: 55000 | H96: Full season | I96: =G96/10 -> 5500 | J96: https://www.15min.lt/24sek/naujiena/lietuva/zalgirieciu-dominavimas-daugiausiai-uzdirbanciu-lkl-zaideju-top-40-875-1641660 | K96: https://www.basketnews.lt/news-166796-labiausiai-verte-pasikele-lkl-zaidejai-dabartine-alga-ir-ko-tiketis-vasara.html
B97: Player | C97: Donatas Sabeckis | D97: Lithuania | E97: Šiauliai | F97: 21/22 | G97: 65000 | H97: Full season | I97: =G97/10 -> 6500 | J97: https://www.15min.lt/24sek/naujiena/lietuva/zalgirieciu-dominavimas-daugiausiai-uzdirbanciu-lkl-zaideju-top-40-875-1641660
B98: Player | C98: Julius Jucikas | D98: Lithuania | E98: Klaipėdos Neptūnas | F98: 21/22 | G98: 65000 | H98: Full season | I98: =G98/10 -> 6500 | J98: https://www.15min.lt/24sek/naujiena/lietuva/zalgirieciu-dominavimas-daugiausiai-uzdirbanciu-lkl-zaideju-top-40-875-1641660
B99: Player | C99: Benas Griciūnas | D99: Lithuania | E99: Klaipėdos Neptūnas | F99: 21/22 | G99: 65000 | H99: Full season | I99: =G99/10 -> 6500 | J99: https://www.15min.lt/24sek/naujiena/lietuva/zalgirieciu-dominavimas-daugiausiai-uzdirbanciu-lkl-zaideju-top-40-875-1641660
B100: Player | C100: Žygimantas Janavičius | D100: Lithuania | E100: Klaipėdos Neptūnas | F100: 21/22 | G100: 65000 | H100: Full season | I100: =G100/10 -> 6500 | J100: https://www.15min.lt/24sek/naujiena/lietuva/zalgirieciu-dominavimas-daugiausiai-uzdirbanciu-lkl-zaideju-top-40-875-1641660
B101: Player | C101: Vytenis Lipkevičius | D101: Lithuania | E101: Lietkabelis | F101: 21/22 | G101: 65000 | H101: Full season | I101: =G101/10 -> 6500 | J101: https://www.15min.lt/24sek/naujiena/lietuva/zalgirieciu-dominavimas-daugiausiai-uzdirbanciu-lkl-zaideju-top-40-875-1641660
B102: Player | C102: Gediminas Orelik | D102: Lithuania | E102: Lietkabelis | F102: 21/22 | G102: 65000 | H102: Full season | I102: =G102/10 -> 6500 | J102: https://www.15min.lt/24sek/naujiena/lietuva/zalgirieciu-dominavimas-daugiausiai-uzdirbanciu-lkl-zaideju-top-40-875-1641660 | K102: https://www.basketnews.lt/news-166796-labiausiai-verte-pasikele-lkl-zaidejai-dabartine-alga-ir-ko-tiketis-vasara.html
B103: Player | C103: Juan Palacios | D103: Lithuania | E103: Jonava | F103: 21/22 | G103: 70000 | H103: Full season | I103: =G103/10 -> 7000 | J103: https://www.15min.lt/24sek/naujiena/lietuva/zalgirieciu-dominavimas-daugiausiai-uzdirbanciu-lkl-zaideju-top-40-875-1641660
B104: Player | C104: Žygimantas Skučas | D104: Lithuania | E104: Pasvalio Pieno Žvaigždės | F104: 21/22 | G104: 70000 | H104: Full season | I104: =G104/10 -> 7000 | J104: https://www.15min.lt/24sek/naujiena/lietuva/zalgirieciu-dominavimas-daugiausiai-uzdirbanciu-lkl-zaideju-top-40-875-1641660
B105: Player | C105: Rokas Gustys | D105: Lithuania | E105: Utenos Juventus | F105: 21/22 | G105: 70000 | H105: Full season | I105: =G105/10 -> 7000 | J105: https://www.15min.lt/24sek/naujiena/lietuva/zalgirieciu-dominavimas-daugiausiai-uzdirbanciu-lkl-zaideju-top-40-875-1641660
B106: Player | C106: Adas Juškevičius | D106: Lithuania | E106: Rytas Vilnius | F106: 14/15 | G106: 100000 | H106: Full season | I106: =G106/10 -> 10000 | J106: https://www.basketnews.lt/news-83614-kiek-uzdirba-didziuju-lkl-klubu-krepsininkai.html
B107: Player | C107: Simas Jasaitis | D107: Lithuania | E107: Rytas Vilnius | F107: 14/15 | G107: 100000 | H107: Full season | I107: =G107/10 -> 10000 | J107: https://www.basketnews.lt/news-83614-kiek-uzdirba-didziuju-lkl-klubu-krepsininkai.html
B108: Player | C108: Billy Baron | D108: Lithuania | E108: Rytas Vilnius | F108: 14/15 | G108: 100000 | H108: Full season | I108: =G108/10 -> 10000 | J108: https://www.basketnews.lt/news-83614-kiek-uzdirba-didziuju-lkl-klubu-krepsininkai.html
B109: Player | C109: Karolis Lukošiūnas | D109: Lithuania | E109: Kauno Žalgiris | F109: 21/22 | G109: 100000 | H109: Full season | I109: =G109/10 -> 10000 | J109: https://www.15min.lt/24sek/naujiena/lietuva/vertinami-ir-svetur-ir-lietuvoje-geriausiai-apmokamu-lietuvos-krepsininku-top-30-875-1641654
B110: Player | C110: Laurynas Beliauskas | D110: Spain | E110: Obradoiro | F110: 21/22 | G110: 100000 | H110: Full season | I110: =G110/10 -> 10000 | J110: https://www.15min.lt/24sek/naujiena/lietuva/vertinami-ir-svetur-ir-lietuvoje-geriausiai-apmokamu-lietuvos-krepsininku-top-30-875-1641654
...

Sheet Notes
K4: zvezda
K5: real
K6: partizan
K7: maccabi
K8: zalgiris
D9: https://www.codesports.com.au/basketball/nbl/nbl-rich-list-the-leagues-highest-paid-player-revealed/news-story/7866be502730868a77169f1f2856db47
D10: https://www.codesports.com.au/basketball/nbl/nbl-bestfive-salaries-revealed-how-one-team-made-mockery-of-1m-pay-gap/news-story/11236aedcbe8c0e7de112b82d144ffe1
D11: https://www.codesports.com.au/basketball/nbl/the-true-cost-of-nbl-success-revealed-in-new-salary-cap-spending-figures/news-story/1c36297db11ed850a8217c70dafb8f92
D13: https://sports.walla.co.il/item/1656259
D14: https://www.globes.co.il/news/article.aspx?did=1000820527
D15: https://www.globes.co.il/news/article.aspx?did=1000483989
D16: https://www.globes.co.il/news/article.aspx?did=1001069020
D17: https://www.globes.co.il/news/article.aspx?did=1000867378
D22: https://www.basketnews.lt/news-132027-mindaugas-kupsas-keliasi-i-jeruzales-hapoel.html?fbclid=IwY2xjawSn9XRleHRuA2FlbQIxMQBicmlkETBRa2FRZjNJbGxOWWRyTHNzc3J0YwZhcHBfaWQQMjIyMDM5MTc4ODIwMDg5MgABHlm5BCQ9jSwT8P3jFbaUb1T0hNZeRWcXnY2RiFZPQk9Syf7avvwq6EYBjFFV_aem_iZGGco9Mo0F0VyMHyS3P-w
D23: https://www.krepsinis.net/naujiena/atskleistos-prancuzijos-lygos-zaideju-ir-treneriu-algos-tarp-kuriu-ir-d-motiejuno/317346
D24: https://www.krepsinis.net/naujiena/o-samhanas-su-zalgiriu-buvo-sudares-1-4-mln-jav-doleriu-vertes-sutarti/238549
D26: https://sportando.basketball/cameron-hunt-unicaja-malaga-joventut/
... D58: https://www.sport5.co.il/articles.aspx?FolderID=274&docID=561038

Sheet Taxes
B6: Germany | C6: 22/23 | D6: Individuals in Germany are taxed between 14 and 42 percent for taxable income ranging from 11,600 and 66,700 euros. The tax rate is 42 percent up for until 277,000 euros and then is 45 percent for more than that. For an unmarried player with no children, a net salary of 60,000 euros needs a gross salary of 133,500 euros, according to the German league. A net salary of 120,000 euros costs a club a gross salary of 244,500 euros. | E6: https://takingthecharge.substack.com/p/follow-the-money-why-germanys-top
B7: Spain | C7: 22/23 | D7: Spain’s tax situation is a bit different than Germany - though the top rates are actually higher depending on region. The usual rate ranges from 45 to 54 percent with Madrid at 45 percent, Barcelona at 52 percent and Valencia at 54 percent. The tax rate in the northern Spanish area Basque Country, however, is only 20-22 percent with the major clubs there being Baskonia and Bilbao. One major difference in Spain is if you are a non-resident, meaning you are in the country for 182 days or fewer. Then you are only taxed at 24 percent. If a player stays in the country a second season, they then fall under the higher rates. But a player can stay in Spain for one season at 24 percent and then leave the country for a season and return and they are once again taxed at 24 percent - but just for that first season back
B8: Greece | C8: 22/23 | D8: The tax rate in Greece is 22 percent, which changed more than 4 years ago after the country’s financial collapse. It had been 40-45 percent up to 100,000 euros and then up to 55 percent for up to 1 million euros. There was a luxury tax for more than that. For example, when Vasilis Spanoulis signed with Olympiacos in 2010 the club paid 5.1 million euros for his 2.4 million euro net salary.
B9: https://x.com/baekpd1983/status/2075466142232326546
